Workbook

Sheet summary
A1: system | B1: model | C1: context_precision | D1: context_recall | E1: faithfullness | F1: answer_correctness | G1: response_time
A2: basic_rag | B2: llama | C2: =result!Q197 -> 0.61794872 | D2: =result!S197 -> 0.53923077 | E2: =result!U197 -> 0.97755789 | F2: =result!W197 -> 0.40769231 | G2: 7.4147157
A3: basic_rag | B3: gemma | C3: =result!Y197 -> 0.64358974 | D3: =result!AA197 -> 0.5642735 | E3: =result!AC197 -> 0.97395829 | F3: =result!AE197 -> 0.42102564 | G3: 5.8762542
A4: basic_rag | B4: deepseek | C4: 0.63333333 | D4: 0.53837607 | E4: 0.97295649 | F4: =result!AM197 -> 0.4425641 | G4: 19.010033
A5: advanced_rag | B5: llama | C5: =result!AO197 -> 0.28974359 | D5: =result!AQ197 -> 0.31017094 | E5: =result!AS197 -> 0.96854701 | F5: =result!AU197 -> 0.22820513 | G5: 22.899666
A6: advanced_rag | B6: gemma | C6: 0.31282051 | D6: 0.29051282 | E6: 0.96191697 | F6: =result!BC197 -> 0.23641026 | G6: 15.421405
A7: advanced_rag | B7: deepseek | C7: =result!BE197 -> 0.32820513 | D7: =result!BG197 -> 0.30333333 | E7: =result!BI197 -> 0.980407 | F7: 0.27948718 | G7: 82.615385

Sheet result
A1: index | B1: user_query | C1: ref_answer | D1: ref_context | E1: l1_response | F1: g1_response | G1: d1_response | H1: l1_retrieved_context | I1: g1_retrieved_context | J1: d1_retrieved_context | K1: l2_response | L1: g2_response | M1: d2_response | N1: l2_retrieved_context | O1: g2_retrieved_context | P1: d2_retrieved_context | Q1: l1_contextual_precision_score | R1: l1_contextual_precision_reason | S1: l1_contextual_recall_score | T1: l1_contextual_recall_reason | U1: l1_faithfulness_score | V1: l1_faithfulness_reason | W1: L1_answer_correctness_score | X1: l1_answer_correctness_reason | Y1: g1_contextual_precision_score | Z1: g1_contextual_precision_reason | AA1: g1_contextual_recall_score | AB1: g1_contextual_recall_reason | AC1: g1_faithfulness_score | AD1: g1_faithfulness_reason | AE1: answer_correctness_score | AF1: answer_correctness_reason | AG1: d1_contextual_precision_score | AH1: d1_contextual_precision_reason | AI1: d1_contextual_recall_score | AJ1: d1_contextual_recall_reason | AK1: d1_faithfulness_score | AL1: d1_faithfulness_reason | AM1: answer_correctness_score | AN1: answer_correctness_reason | AO1: l2_contextual_precision_score | AP1: l2_contextual_precision_reason | AQ1: l2_contextual_recall_score | AR1: l2_contextual_recall_reason | AS1: l2_faithfulness_score | AT1: l2_faithfulness_reason | AU1: l2_answer_correctness_score | AV1: l2_answer_correctness_reason | AW1: g2_contextual_precision_score | AX1: g2_contextual_precision_reason | AY1: g2_contextual_recall_score | AZ1: g2_contextual_recall_reason | BA1: g2_faithfulness_score | BB1: g2_faithfulness_reason | BC1: g2_answer_correctness_score | BD1: g2_answer_correctness_reason | BE1: d2_contextual_precision_score | BF1: d2_contextual_precision_reason | BG1: d2_contextual_recall_score | BH1: d2_contextual_recall_reason | BI1: d2_faithfulness_score | BJ1: d2_faithfulness_reason | BK1: d2_answer_correctness_score | BL1: d2_answer_correctness_reason | BM1: data_type
A2: 1 | B2: Which month is set aside each year in the UAE for nationwide reading and literacy activities, including those associated with the Abu Dhabi Reads campaign? | C2: March | D2: Building on the Abu Dhabi Reads campaign launched in 2013, the month of March is dedicated annually to raising awareness of literacy in the community and in schools | E2: To answer this question, I will walk you through my thought process step by step. Step 1: Read the context carefully to understand the information provided. Step 2: Identify relevant sentences that may provide the answer. Step 3: Analyze each sentence for relevance and look for specific details. Upon reviewing the context, I found the following sentence: "Building on the Abu Dhabi Reads campaign launched in 2013, the month of March is dedicated annually to raising awareness of literacy in the community and in schools." Based on this sentence, it appears that the month set aside each year for nationwide reading and literacy activities, including those associated with the Abu Dhabi Reads campaign, is: March Therefore, my answer is: March | F2: Okay, let's break this down step by step to answer the question. 1. **Understand the Question:** The question asks about the specific month dedicated to reading and literacy activities in the UAE, particularly referencing the "Abu Dhabi Reads" campaign. 2. **Scan the Context:** I need to find the information within the provided text that answers this question. I'll quickly read through the entire text to locate relevant details. 3. **Identify the Relevant Information:** The text states: "Building on the Abu Dhabi Reads campaign launched in 2013, the month of March is dedicated annually to raising awareness of literacy in the community and in schools." 4. **Formulate the Answer:** Based on the information found, the answer is March. **Answer:** March | G2: March is set aside each year in the UAE for nationwide reading and literacy activities, including those associated with the Abu Dhabi Reads campaign. | H2: ['international reading performance benchmark for the Emirate. In 2016, the Emirate participated \nagain with nationally representative samples from schools that also included participation in the \nePIRLS assessment. The UAE Government recognizes the results of high -quality international \nassessments in the provision of insights and contribution toward improving education quality. \nAbu Dhabi has been undergoing significant education and systemic reform to standardize its \neducation models to meet the objectives of the National Agenda. Considering the substantial and \nongoing transformations, measuring significant impact could be considered premature. However, \nGovernment at the fed eral and n ational level s leveraged the results to strategize and promote \nreading initiatives for all schools and communities. Building on the Abu Dhabi Reads campaign \nlaunched in 2013, the month of March is dedicated annually to raising awareness of literacy in the \ncommunity and in schools.\n3', 'international reading performance benchmark for the Emirate. In 2016, the Emirate participated \nagain with nationally representative samples from schools that also included participation in the \nePIRLS assessment. The UAE Government recognizes the results of high -quality international \nassessments in the provision of insights and contribution toward improving education quality. \nAbu Dhabi has been undergoing significant education and systemic reform to standardize its \neducation models to meet the objectives of the National Agenda. Considering the substantial and \nongoing transformations, measuring significant impact could be considered premature. However, \nGovernment at the fed eral and n ational level s leveraged the results to strategize and promote \nreading initiatives for all schools and communities. Building on the Abu Dhabi Reads campaign \nlaunched in 2013, the month of March is dedicated annually to raising awareness of literacy in the \ncommunity and in schools.\n3', 'international reading performance benchmark for the Emirate. In 2016, the Emirate participated \nagain with nationally representative samples from schools that also included participation in the \nePIRLS assessment. The UAE Government recognizes the results of high -quality international \nassessments in the provision of insights and contribution toward improving education quality. \nAbu Dhabi has been undergoing significant education and systemic reform to standardize its \neducation models to meet the objectives of the National Agenda. Considering the substantial and \nongoing transformations, measuring significant impact could be considered premature. However, \nGovernment at the fed eral and n ational level s leveraged the results to strategize and promote \nreading initiatives for all schools and communities. Building on the Abu Dhabi Reads campaign \nlaunched in 2013, the month of March is dedicated annually to raising awareness of literacy in the \ncommunity and in schools.\n3', 'international reading performance benchmark for the Emirate. In 2016, the Emirate participated \nagain with nationally representative samples from schools that also included participation in the \nePIRLS assessment. The UAE Government recognizes the results of high -quality international \nassessments in the provision of insights and contribution toward improving education quality. \nAbu Dhabi has been undergoing significant education and systemic reform to standardize its \neducation models to meet the objectives of the National Agenda. Considering the substantial and \nongoing transformations, measuring significant impact could be considered premature. However, \nGovernment at the fed eral and n ational level s leveraged the results to strategize and promote \nreading initiatives for all schools and communities. Building on the Abu Dhabi Reads campaign \nlaunched in 2013, the month of March is dedicated annually to raising awareness of literacy in the \ncommunity and in schools.\n3'] | I2: ['international reading performance benchmark for the Emirate. In 2016, the Emirate participated \nagain with nationally representative samples from schools that also included participation in the \nePIRLS assessment. The UAE Government recognizes the results of high -quality international \nassessments in the provision of insights and contribution toward improving education quality. \nAbu Dhabi has been undergoing significant education and systemic reform to standardize its \neducation models to meet the objectives of the National Agenda. Considering the substantial and \nongoing transformations, measuring significant impact could be considered premature. However, \nGovernment at the fed eral and n ational level s leveraged the results to strategize and promote \nreading initiatives for all schools and communities. Building on the Abu Dhabi Reads campaign \nlaunched in 2013, the month of March is dedicated annually to raising awareness of literacy in the \ncommunity and in schools.\n3', 'international reading performance benchmark for the Emirate. In 2016, the Emirate participated \nagain with nationally representative samples from schools that also included participation in the \nePIRLS assessment. The UAE Government recognizes the results of high -quality international \nassessments in the provision of insights and contribution toward improving education quality. \nAbu Dhabi has been undergoing significant education and systemic reform to standardize its \neducation models to meet the objectives of the National Agenda. Considering the substantial and \nongoing transformations, measuring significant impact could be considered premature. However, \nGovernment at the fed eral and n ational level s leveraged the results to strategize and promote \nreading initiatives for all schools and communities. Building on the Abu Dhabi Reads campaign \nlaunched in 2013, the month of March is dedicated annually to raising awareness of literacy in the \ncommunity and in schools.\n3', 'international reading performance benchmark for the Emirate. In 2016, the Emirate participated \nagain with nationally representative samples from schools that also included participation in the \nePIRLS assessment. The UAE Government recognizes the results of high -quality international \nassessments in the provision of insights and contribution toward improving education quality. \nAbu Dhabi has been undergoing significant education and systemic reform to standardize its \neducation models to meet the objectives of the National Agenda. Considering the substantial and \nongoing transformations, measuring significant impact could be considered premature. However, \nGovernment at the fed eral and n ational level s leveraged the results to strategize and promote \nreading initiatives for all schools and communities. Building on the Abu Dhabi Reads campaign \nlaunched in 2013, the month of March is dedicated annually to raising awareness of literacy in the \ncommunity and in schools.\n3', 'international reading performance benchmark for the Emirate. In 2016, the Emirate participated \nagain with nationally representative samples from schools that also included participation in the \nePIRLS assessment. The UAE Government recognizes the results of high -quality international \nassessments in the provision of insights and contribution toward improving education quality. \nAbu Dhabi has been undergoing significant education and systemic reform to standardize its \neducation models to meet the objectives of the National Agenda. Considering the substantial and \nongoing transformations, measuring significant impact could be considered premature. However, \nGovernment at the fed eral and n ational level s leveraged the results to strategize and promote \nreading initiatives for all schools and communities. Building on the Abu Dhabi Reads campaign \nlaunched in 2013, the month of March is dedicated annually to raising awareness of literacy in the \ncommunity and in schools.\n3'] | J2: ['international reading performance benchmark for the Emirate. In 2016, the Emirate participated \nagain with nationally representative samples from schools that also included participation in the \nePIRLS assessment. The UAE Government recognizes the results of high -quality international \nassessments in the provision of insights and contribution toward improving education quality. \nAbu Dhabi has been undergoing significant education and systemic reform to standardize its \neducation models to meet the objectives of the National Agenda. Considering the substantial and \nongoing transformations, measuring significant impact could be considered premature. However, \nGovernment at the fed eral and n ational level s leveraged the results to strategize and promote \nreading initiatives for all schools and communities. Building on the Abu Dhabi Reads campaign \nlaunched in 2013, the month of March is dedicated annually to raising awareness of literacy in the \ncommunity and in schools.\n3', 'international reading performance benchmark for the Emirate. In 2016, the Emirate participated \nagain with nationally representative samples from schools that also included participation in the \nePIRLS assessment. The UAE Government recognizes the results of high -quality international \nassessments in the provision of insights and contribution toward improving education quality. \nAbu Dhabi has been undergoing significant education and systemic reform to standardize its \neducation models to meet the objectives of the National Agenda. Considering the substantial and \nongoing transformations, measuring significant impact could be considered premature. However, \nGovernment at the fed eral and n ational level s leveraged the results to strategize and promote \nreading initiatives for all schools and communities. Building on the Abu Dhabi Reads campaign \nlaunched in 2013, the month of March is dedicated annually to raising awareness of literacy in the \ncommunity and in schools.\n3', 'international reading performance benchmark for the Emirate. In 2016, the Emirate participated \nagain with nationally representative samples from schools that also included participation in the \nePIRLS assessment. The UAE Government recognizes the results of high -quality international \nassessments in the provision of insights and contribution toward improving education quality. \nAbu Dhabi has been undergoing significant education and systemic reform to standardize its \neducation models to meet the objectives of the National Agenda. Considering the substantial and \nongoing transformations, measuring significant impact could be considered premature. However, \nGovernment at the fed eral and n ational level s leveraged the results to strategize and promote \nreading initiatives for all schools and communities. Building on the Abu Dhabi Reads campaign \nlaunched in 2013, the month of March is dedicated annually to raising awareness of literacy in the \ncommunity and in schools.\n3', 'international reading performance benchmark for the Emirate. In 2016, the Emirate participated \nagain with nationally representative samples from schools that also included participation in the \nePIRLS assessment. The UAE Government recognizes the results of high -quality international \nassessments in the provision of insights and contribution toward improving education quality. \nAbu Dhabi has been undergoing significant education and systemic reform to standardize its \neducation models to meet the objectives of the National Agenda. Considering the substantial and \nongoing transformations, measuring significant impact could be considered premature. However, \nGovernment at the fed eral and n ational level s leveraged the results to strategize and promote \nreading initiatives for all schools and communities. Building on the Abu Dhabi Reads campaign \nlaunched in 2013, the month of March is dedicated annually to raising awareness of literacy in the \ncommunity and in schools.\n3'] | K2: Based on the information provided, the final answer to the main question is: The month set aside each year in the UAE for nationwide reading and literacy activities, including those associated with the Abu Dhabi Reads campaign, is March. | L2: The UAE designates March annually as the month for nationwide reading and literacy activities. This initiative is heavily supported by the Abu Dhabi Reads campaign, which launched in 2013 and focuses on raising awareness of literacy within the community and schools. The campaign’s annual focus on March underscores the UAE’s commitment to promoting reading and improving literacy rates across the nation. | M2: Based on the provided information, the UAE designates **March** annually for nationwide reading and literacy activities, and the Abu Dhabi Reads campaign is part of these initiatives. Therefore, the month set aside is **March**. | N2: international reading performance benchmark for the Emirate. In 2016, the Emirate participated again with nationally representative samples from schools that also included participation in the ePIRLS assessment. The UAE Government recognizes the results of high -quality international assessments in the provision of insights and contribution toward improving education quality. Abu Dhabi has been undergoing significant education and systemic reform to standardize its education models to meet the objectives of the National Agenda. Considering the substantial and ongoing transformations, measuring significant impact could be considered premature. However, Government at the fed eral and n ational level s leveraged the results to strategize and promote reading initiatives for all schools and communities. Building on the Abu Dhabi Reads campaign launched in 2013, the month of March is dedicated annually to raising awareness of literacy in the community and in schools. 3 international reading performance benchmark for the Emirate. In 2016, the Emirate participated again with nationally representative samples from schools that also included participation in the ePIRLS assessment. The UAE Government recognizes the results of high -quality international assessments in the provision of insights and contribution toward improving education quality. Abu Dhabi has been undergoing significant education and systemic reform to standardize its education models to meet the objectives of the National Agenda. Considering the substantial and ongoing transformations, measuring significant impact could be considered premature. However, Government at the fed eral and n ational level s leveraged the results to strategize and promote reading initiatives for all schools and communities. Building on the Abu Dhabi Reads campaign launched in 2013, the month of March is dedicated annually to raising awareness of literacy in the community and in schools. 3 international reading performance benchmark for the Emirate. In 2016, the Emirate participated again with nationally representative samples from schools that also included participation in the ePIRLS assessment. The UAE Government recognizes the results of high -quality international assessments in the provision of insights and contribution toward improving education quality. Abu Dhabi has been undergoing significant education and systemic reform to standardize its education models to meet the objectives of the National Agenda. Considering the substantial and ongoing transformations, measuring significant impact could be considered premature. However, Government at the fed eral and n ational level s leveraged the results to strategize and promote reading initiatives for all schools and communities. Building on the Abu Dhabi Reads campaign launched in 2013, the month of March is dedicated annually to raising awareness of literacy in the community and in schools. 3 international reading performance benchmark for the Emirate. In 2016, the Emirate participated again with nationally representative samples from schools that also included participation in the ePIRLS assessment. The UAE Government recognizes the results of high -quality international assessments in the provision of insights and contribution toward improving education quality. Abu Dhabi has been undergoing significant education and systemic reform to standardize its education models to meet the objectives of the National Agenda. Considering the substantial and ongoing transformations, measuring significant impact could be considered premature. However, Government at the fed eral and n ational level s leveraged the results to strategize and promote reading initiatives for all schools and communities. Building on the Abu Dhabi Reads campaign launched in 2013, the month of March is dedicated annually to raising awareness of literacy in the community and in schools. 3 international reading performance benchmark for the Emirate. In 2016, the Emirate participated again with nationally representative samples from schools that also included participation in the ePIRLS assessment. The UAE Government recognizes the results of high -quality international assessments in the provision of insights and contribution toward improving education quality. Abu Dhabi has been undergoing significant education and systemic reform to standardize its education models to meet the objectives of the National Agenda. Considering the substantial and ongoing transformations, measuring significant impact could be considered premature. However, Government at the fed eral and n ational level s leveraged the results to strategize and promote reading initiatives for all schools and communities. Building on the Abu Dhabi Reads campaign launched in 2013, the month of March is dedicated annually to raising awareness of literacy in the community and in schools. 3 international reading performance benchmark for the Emirate. In 2016, the Emirate participated again with nationally representative samples from schools that also included participation in the ePIRLS assessment. The UAE Government recognizes the results of high -quality international assessments in the provision of insights and contribution toward improving education quality. Abu Dhabi has been undergoing significant education and systemic reform to standardize its education models to meet the objectives of the National Agenda. Considering the substantial and ongoing transformations, measuring significant impact could be considered premature. However, Government at the fed eral and n ational level s leveraged the results to strategize and promote reading initiatives for all schools and communities. Building on the Abu Dhabi Reads campaign launched in 2013, the month of March is dedicated annually to raising awareness of literacy in the community and in schools. 3 international reading performance benchmark for the Emirate. In 2016, the Emirate participated again with nationally representative samples from schools that also included participation in the ePIRLS assessment. The UAE Government recognizes the results of high -quality international assessments in the provision of insights and contribution toward improving education quality. Abu Dhabi has been undergoing significant education and systemic reform to standardize its education models to meet the objectives of the National Agenda. Considering the substantial and ongoing transformations, measuring significant impact could be considered premature. However, Government at the fed eral and n ational level s leveraged the results to strategize and promote reading initiatives for all schools and communities. Building on the Abu Dhabi Reads campaign launched in 2013, the month of March is dedicated annually to raising awareness of literacy in the community and in schools. 3 international reading performance benchmark for the Emirate. In 2016, the Emirate participated again with nationally representative samples from schools that also included participation in the ePIRLS assessment. The UAE Government recognizes the results of high -quality international assessments in the provision of insights and contribution toward improving education quality. Abu Dhabi has been undergoing significant education and systemic reform to standardize its education models to meet the objectives of the National Agenda. Considering the substantial and ongoing transformations, measuring significant impact could be considered premature. However, Government at the fed eral and n ational level s leveraged the results to strategize and promote reading initiatives for all schools and communities. Building on the Abu Dhabi Reads campaign launched in 2013, the month of March is dedicated annually to raising awareness of literacy in the community and in schools. 3 | O2: ['international reading performance benchmark for the Emirate. In 2016, the Emirate participated \nagain with nationally representative samples from schools that also included participation in the \nePIRLS assessment. The UAE Government recognizes the results of high -quality international \nassessments in the provision of insights and contribution toward improving education quality. \nAbu Dhabi has been undergoing significant education and systemic reform to standardize its \neducation models to meet the objectives of the National Agenda. Considering the substantial and \nongoing transformations, measuring significant impact could be considered premature. However, \nGovernment at the fed eral and n ational level s leveraged the results to strategize and promote \nreading initiatives for all schools and communities. Building on the Abu Dhabi Reads campaign \nlaunched in 2013, the month of March is dedicated annually to raising awareness of literacy in the \ncommunity and in schools.\n3\n\ninternational reading performance benchmark for the Emirate. In 2016, the Emirate participated \nagain with nationally representative samples from schools that also included participation in the \nePIRLS assessment. The UAE Government recognizes the results of high -quality international \nassessments in the provision of insights and contribution toward improving education quality. \nAbu Dhabi has been undergoing significant education and systemic reform to standardize its \neducation models to meet the objectives of the National Agenda. Considering the substantial and \nongoing transformations, measuring significant impact could be considered premature. However, \nGovernment at the fed eral and n ational level s leveraged the results to strategize and promote \nreading initiatives for all schools and communities. Building on the Abu Dhabi Reads campaign \nlaunched in 2013, the month of March is dedicated annually to raising awareness of literacy in the \ncommunity and in schools.\n3\n\ninternational reading performance benchmark for the Emirate. In 2016, the Emirate participated \nagain with nationally representative samples from schools that also included participation in the \nePIRLS assessment. The UAE Government recognizes the results of high -quality international \nassessments in the provision of insights and contribution toward improving education quality. \nAbu Dhabi has been undergoing significant education and systemic reform to standardize its \neducation models to meet the objectives of the National Agenda. Considering the substantial and \nongoing transformations, measuring significant impact could be considered premature. However, \nGovernment at the fed eral and n ational level s leveraged the results to strategize and promote \nreading initiatives for all schools and communities. Building on the Abu Dhabi Reads campaign \nlaunched in 2013, the month of March is dedicated annually to raising awareness of literacy in the \ncommunity and in schools.\n3\n\ninternational reading performance benchmark for the Emirate. In 2016, the Emirate participated \nagain with nationally representative samples from schools that also included participation in the \nePIRLS assessment. The UAE Government recognizes the results of high -quality international \nassessments in the provision of insights and contribution toward improving education quality. \nAbu Dhabi has been undergoing significant education and systemic reform to standardize its \neducation models to meet the objectives of the National Agenda. Considering the substantial and \nongoing transformations, measuring significant impact could be considered premature. However, \nGovernment at the fed eral and n ational level s leveraged the results to strategize and promote \nreading initiatives for all schools and communities. Building on the Abu Dhabi Reads campaign \nlaunched in 2013, the month of March is dedicated annually to raising awareness of literacy in the \ncommunity and in schools.\n3\n\ninternational reading performance benchmark for the Emirate. In 2016, the Emirate participated \nagain with nationally representative samples from schools that also included participation in the \nePIRLS assessment. The UAE Government recognizes the results of high -quality international \nassessments in the provision of insights and contribution toward improving education quality. \nAbu Dhabi has been undergoing significant education and systemic reform to standardize its \neducation models to meet the objectives of the National Agenda. Considering the substantial and \nongoing transformations, measuring significant impact could be considered premature. However, \nGovernment at the fed eral and n ational level s leveraged the results to strategize and promote \nreading initiatives for all schools and communities. Building on the Abu Dhabi Reads campaign \nlaunched in 2013, the month of March is dedicated annually to raising awareness of literacy in the \ncommunity and in schools.\n3\n\ninternational reading performance benchmark for the Emirate. In 2016, the Emirate participated \nagain with nationally representative samples from schools that also included participation in the \nePIRLS assessment. The UAE Government recognizes the results of high -quality international \nassessments in the provision of insights and contribution toward improving education quality. \nAbu Dhabi has been undergoing significant education and systemic reform to standardize its \neducation models to meet the objectives of the National Agenda. Considering the substantial and \nongoing transformations, measuring significant impact could be considered premature. However, \nGovernment at the fed eral and n ational level s leveraged the results to strategize and promote \nreading initiatives for all schools and communities. Building on the Abu Dhabi Reads campaign \nlaunched in 2013, the month of March is dedicated annually to raising awareness of literacy in the \ncommunity and in schools.\n3\n\ninternational reading performance benchmark for the Emirate. In 2016, the Emirate participated \nagain with nationally representative samples from schools that also included participation in the \nePIRLS assessment. The UAE Government recognizes the results of high -quality international \nassessments in the provision of insights and contribution toward improving education quality. \nAbu Dhabi has been undergoing significant education and systemic reform to standardize its \neducation models to meet the objectives of the National Agenda. Considering the substantial and \nongoing transformations, measuring significant impact could be considered premature. However, \nGovernment at the fed eral and n ational level s leveraged the results to strategize and promote \nreading initiatives for all schools and communities. Building on the Abu Dhabi Reads campaign \nlaunched in 2013, the month of March is dedicated annually to raising awareness of literacy in the \ncommunity and in schools.\n3\n\ninternational reading performance benchmark for the Emirate. In 2016, the Emirate participated \nagain with nationally representative samples from schools that also included participation in the \nePIRLS assessment. The UAE Government recognizes the results of high -quality international \nassessments in the provision of insights and contribution toward improving education quality. \nAbu Dhabi has been undergoing significant education and systemic reform to standardize its \neducation models to meet the objectives of the National Agenda. Considering the substantial and \nongoing transformations, measuring significant impact could be considered premature. However, \nGovernment at the fed eral and n ational level s leveraged the results to strategize and promote \nreading initiatives for all schools and communities. Building on the Abu Dhabi Reads campaign \nlaunched in 2013, the month of March is dedicated annually to raising awareness of literacy in the \ncommunity and in schools.\n3\n\ninternational reading performance benchmark for the Emirate. In 2016, the Emirate participated \nagain with nationally representative samples from schools that also included participation in the \nePIRLS assessment. The UAE Government recognizes the results of high -quality international \nassessments in the provision of insights and contribution toward improving education quality. \nAbu Dhabi has been undergoing significant education and systemic reform to standardize its \neducation models to meet the objectives of the National Agenda. Considering the substantial and \nongoing transformations, measuring significant impact could be considered premature. However, \nGovernment at the fed eral and n ational level s leveraged the results to strategize and promote \nreading initiatives for all schools and communities. Building on the Abu Dhabi Reads campaign \nlaunched in 2013, the month of March is dedicated annually to raising awareness of literacy in the \ncommunity and in schools.\n3\n\ninternational reading performance benchmark for the Emirate. In 2016, the Emirate participated \nagain with nationally representative samples from schools that also included participation in the \nePIRLS assessment. The UAE Government recognizes the results of high -quality international \nassessments in the provision of insights and contribution toward improving education quality. \nAbu Dhabi has been undergoing significant education and systemic reform to standardize its \neducation models to meet the objectives of the National Agenda. Considering the substantial and \nongoing transformations, measuring significant impact could be considered premature. However, \nGovernment at the fed eral and n ational level s leveraged the results to strategize and promote \nreading initiatives for all schools and communities. Building on the Abu Dhabi Reads campaign \nlaunched in 2013, the month of March is dedicated annually to raising awareness of literacy in the \ncommunity and in schools.\n3\n\ninternational reading performance benchmark for the Emirate. In 2016, the Emirate participated \nagain with nationally representative samples from schools that also included participation in the \nePIRLS assessment. The UAE Government recognizes the results of high -quality international \nassessments in the provision of insights and contribution toward improving education quality. \nAbu Dhabi has been undergoing significant education and systemic reform to standardize its \neducation models to meet the objectives of the National Agenda. Considering the substantial and \nongoing transformations, measuring significant impact could be considered premature. However, \nGovernment at the fed eral and n ational level s leveraged the results to strategize and promote \nreading initiatives for all schools and communities. Building on the Abu Dhabi Reads campaign \nlaunched in 2013, the month of March is dedicated annually to raising awareness of literacy in the \ncommunity and in schools.\n3\n\ninternational reading performance benchmark for the Emirate. In 2016, the Emirate participated \nagain with nationally representative samples from schools that also included participation in the \nePIRLS assessment. The UAE Government recognizes the results of high -quality international \nassessments in the provision of insights and contribution toward improving education quality. \nAbu Dhabi has been undergoing significant education and systemic reform to standardize its \neducation models to meet the objectives of the National Agenda. Considering the substantial and \nongoing transformations, measuring significant impact could be considered premature. However, \nGovernment at the fed eral and n ational level s leveraged the results to strategize and promote \nreading initiatives for all schools and communities. Building on the Abu Dhabi Reads campaign \nlaunched in 2013, the month of March is dedicated annually to raising awareness of literacy in the \ncommunity and in schools.\n3'] | P2: ['international reading performance benchmark for the Emirate. In 2016, the Emirate participated \nagain with nationally representative samples from schools that also included participation in the \nePIRLS assessment. The UAE Government recognizes the results of high -quality international \nassessments in the provision of insights and contribution toward improving education quality. \nAbu Dhabi has been undergoing significant education and systemic reform to standardize its \neducation models to meet the objectives of the National Agenda. Considering the substantial and \nongoing transformations, measuring significant impact could be considered premature. However, \nGovernment at the fed eral and n ational level s leveraged the results to strategize and promote \nreading initiatives for all schools and communities. Building on the Abu Dhabi Reads campaign \nlaunched in 2013, the month of March is dedicated annually to raising awareness of literacy in the \ncommunity and in schools.\n3\n\ninternational reading performance benchmark for the Emirate. In 2016, the Emirate participated \nagain with nationally representative samples from schools that also included participation in the \nePIRLS assessment. The UAE Government recognizes the results of high -quality international \nassessments in the provision of insights and contribution toward improving education quality. \nAbu Dhabi has been undergoing significant education and systemic reform to standardize its \neducation models to meet the objectives of the National Agenda. Considering the substantial and \nongoing transformations, measuring significant impact could be considered premature. However, \nGovernment at the fed eral and n ational level s leveraged the results to strategize and promote \nreading initiatives for all schools and communities. Building on the Abu Dhabi Reads campaign \nlaunched in 2013, the month of March is dedicated annually to raising awareness of literacy in the \ncommunity and in schools.\n3\n\ninternational reading performance benchmark for the Emirate. In 2016, the Emirate participated \nagain with nationally representative samples from schools that also included participation in the \nePIRLS assessment. The UAE Government recognizes the results of high -quality international \nassessments in the provision of insights and contribution toward improving education quality. \nAbu Dhabi has been undergoing significant education and systemic reform to standardize its \neducation models to meet the objectives of the National Agenda. Considering the substantial and \nongoing transformations, measuring significant impact could be considered premature. However, \nGovernment at the fed eral and n ational level s leveraged the results to strategize and promote \nreading initiatives for all schools and communities. Building on the Abu Dhabi Reads campaign \nlaunched in 2013, the month of March is dedicated annually to raising awareness of literacy in the \ncommunity and in schools.\n3\n\ninternational reading performance benchmark for the Emirate. In 2016, the Emirate participated \nagain with nationally representative samples from schools that also included participation in the \nePIRLS assessment. The UAE Government recognizes the results of high -quality international \nassessments in the provision of insights and contribution toward improving education quality. \nAbu Dhabi has been undergoing significant education and systemic reform to standardize its \neducation models to meet the objectives of the National Agenda. Considering the substantial and \nongoing transformations, measuring significant impact could be considered premature. However, \nGovernment at the fed eral and n ational level s leveraged the results to strategize and promote \nreading initiatives for all schools and communities. Building on the Abu Dhabi Reads campaign \nlaunched in 2013, the month of March is dedicated annually to raising awareness of literacy in the \ncommunity and in schools.\n3\n\ninternational reading performance benchmark for the Emirate. In 2016, the Emirate participated \nagain with nationally representative samples from schools that also included participation in the \nePIRLS assessment. The UAE Government recognizes the results of high -quality international \nassessments in the provision of insights and contribution toward improving education quality. \nAbu Dhabi has been undergoing significant education and systemic reform to standardize its \neducation models to meet the objectives of the National Agenda. Considering the substantial and \nongoing transformations, measuring significant impact could be considered premature. However, \nGovernment at the fed eral and n ational level s leveraged the results to strategize and promote \nreading initiatives for all schools and communities. Building on the Abu Dhabi Reads campaign \nlaunched in 2013, the month of March is dedicated annually to raising awareness of literacy in the \ncommunity and in schools.\n3\n\ninternational reading performance benchmark for the Emirate. In 2016, the Emirate participated \nagain with nationally representative samples from schools that also included participation in the \nePIRLS assessment. The UAE Government recognizes the results of high -quality international \nassessments in the provision of insights and contribution toward improving education quality. \nAbu Dhabi has been undergoing significant education and systemic reform to standardize its \neducation models to meet the objectives of the National Agenda. Considering the substantial and \nongoing transformations, measuring significant impact could be considered premature. However, \nGovernment at the fed eral and n ational level s leveraged the results to strategize and promote \nreading initiatives for all schools and communities. Building on the Abu Dhabi Reads campaign \nlaunched in 2013, the month of March is dedicated annually to raising awareness of literacy in the \ncommunity and in schools.\n3\n\ninternational reading performance benchmark for the Emirate. In 2016, the Emirate participated \nagain with nationally representative samples from schools that also included participation in the \nePIRLS assessment. The UAE Government recognizes the results of high -quality international \nassessments in the provision of insights and contribution toward improving education quality. \nAbu Dhabi has been undergoing significant education and systemic reform to standardize its \neducation models to meet the objectives of the National Agenda. Considering the substantial and \nongoing transformations, measuring significant impact could be considered premature. However, \nGovernment at the fed eral and n ational level s leveraged the results to strategize and promote \nreading initiatives for all schools and communities. Building on the Abu Dhabi Reads campaign \nlaunched in 2013, the month of March is dedicated annually to raising awareness of literacy in the \ncommunity and in schools.\n3\n\ninternational reading performance benchmark for the Emirate. In 2016, the Emirate participated \nagain with nationally representative samples from schools that also included participation in the \nePIRLS assessment. The UAE Government recognizes the results of high -quality international \nassessments in the provision of insights and contribution toward improving education quality. \nAbu Dhabi has been undergoing significant education and systemic reform to standardize its \neducation models to meet the objectives of the National Agenda. Considering the substantial and \nongoing transformations, measuring significant impact could be considered premature. However, \nGovernment at the fed eral and n ational level s leveraged the results to strategize and promote \nreading initiatives for all schools and communities. Building on the Abu Dhabi Reads campaign \nlaunched in 2013, the month of March is dedicated annually to raising awareness of literacy in the \ncommunity and in schools.\n3'] | Q2: 1 | R2: The score is 1.00 because the first node in the retrieval contexts contains the exact answer, stating "the month of March is dedicated annually to raising awareness of literacy in the community and in schools," and there are no irrelevant nodes ranked higher than it. | S2: 1 | T2: The score is 1.00 because the single sentence 'March' is fully supported by node 1 in the retrieval context, which contains the relevant phrase. | U2: 1 | V2: The score is 1.00 because the actual output perfectly aligns with the retrieval context—no contradictions were found, indicating complete faithfulness! | W2: 1 | X2: The actual output correctly states the answer as March, matching the expected single-word answer. It contains no contradictory claims and includes the key point from the expected output. The additional explanatory steps do not affect semantic equivalence, so all evaluation criteria are satisfied. | Y2: 1 | Z2: The score is 1.00 because the only node ranked first contains the exact answer, and there are no irrelevant nodes ranked above it. The node’s reason states, "The context explicitly states that 'the month of March is dedicated annually to raising awareness of literacy in the community and in schools,' which directly answers the question about the month set aside for nationwide reading and literacy activities in the UAE." Since contextual precision cannot exceed 1, the score remains at its maximum. | AA2: 1 | AB2: The score is 1.00 because the expected output 'March' is directly supported by node 1 in the retrieval context, which explicitly mentions March. | AC2: 1 | AD2: The score is 1.00 because there are no contradictions, indicating the actual output perfectly aligns with the retrieval context! | AE2: 1 | AF2: The actual output correctly states that the month dedicated to reading and literacy activities in the UAE is March, matching the expected answer. It contains no contradictory claims and includes all key information required. The additional explanatory steps do not affect the factual correctness, so the response fully satisfies the evaluation criteria. | AG2: 1 | AH2: The score is 1.00 because the first node in the retrieval contexts contains the exact answer, stating "the month of March is dedicated annually to raising awareness of literacy in the community and in schools," and there are no irrelevant nodes ranked higher than it. | AI2: 1 | AJ2: The score is 1.00 because the single sentence 'March' is fully supported by node 1 in the retrieval context, which contains the relevant phrase. | AK2: 1 | AL2: The score is 1.00 because the actual output perfectly aligns with the retrieval context—no contradictions were found, indicating complete faithfulness! | AM2: 1 | AN2: The actual output contains the key point 'March' and no contradictions; it expands on the expected content but still aligns with the factual claim. | AO2: 1 | AP2: The score is 1.00 because the only node ranked first contains the exact answer, quoting "the month of March is dedicated annually to raising awareness of literacy in the community and in schools," and there are no irrelevant nodes ranked higher than it. | AQ2: 1 | AR2: The score is 1.00 because the expected output "March" is directly supported by node 1 in the retrieval context, which explicitly mentions March as the month dedicated to literacy awareness. | AS2: 1 | AT2: The score is 1.00 because there are no contradictions, indicating the output perfectly aligns with the retrieval context! | AU2: 1 | AV2: The actual output correctly states that the month is March, matching the expected answer. It contains no contradictory information and includes the key point from the expected output. The additional explanatory context does not affect semantic equivalence, so all evaluation steps are satisfied. | AW2: 1 | AX2: The score is 1.00 because the only node in the retrieval contexts (node rank 1) is relevant, and there are no irrelevant nodes ranked above it. Since all relevant nodes are already at the top, the contextual precision cannot be higher than 1.00. | AY2: 1 | AZ2: The score is 1.00 because sentence 1 in the expected output directly matches node 1 in the retrieval context, which contains the phrase 'month of March'. | BA2: 1 | BB2: The score is 1.00 because there are no contradictions, indicating the actual output perfectly aligns with the retrieval context! | BC2: 1 | BD2: The actual output correctly identifies March as the key point, matching the expected output. No contradictions are present, and the additional context does not omit any required information. The response is semantically equivalent to the expected answer, satisfying all evaluation criteria. | BE2: 1 | BF2: The score is 1.00 because the only node ranked first contains the exact answer, and there are no irrelevant nodes ranked above it. The node’s reason states, "The context explicitly states that 'the month of March is dedicated annually to raising awareness of literacy in the community and in schools,' which directly answers the question about the month set aside for nationwide reading and literacy activities in the UAE." Since contextual precision cannot exceed 1, the score remains at its maximum. | BG2: 1 | BH2: The score is 1.00 because sentence 1 in the expected output directly matches node 1 in the retrieval context, which contains the phrase 'month of March'. | BI2: 1 | BJ2: The score is 1.00 because there are no contradictions, indicating the actual output perfectly aligns with the retrieval context! | BK2: 1 | BL2: The actual output correctly states March, matching the expected answer, and provides additional context without contradicting the expected content. All key points are present and the meaning is equivalent, so the response fully satisfies the evaluation criteria. | BM2: {=_xlfn.XLOOKUP(B2:B196, [1]faithfulness!$B$2:$B$195,[1]faithfulness!$G$2:$G$195,"synthetic")} -> synthetic
A3: 2 | B3: How many public, private, and charter schools exist in Abu Dhabi? | C3: Abu Dhabi has 218 public schools, 203 private schools, and 22 charter schools. | D3: There are 218 public schools with a student population of 119,261, 80 percent of which are UAE nationals. The remainder are non-native but have Arabic as their first language. Since 2019, 22 charter schools have been established, serving over 30,000 predominately native students in a student-centric education model that provides innovative learning practices in a stimulating environment. Currently there are 203 private schools in Abu Dhabi with UAE nationals accounting for 29 percent of enrollment. The number of students attending private schools has been growing at a compound annual growth rate of 2.4 percent up to 2019. | E3: Let's go through my thought process step by step: 1. I read the context carefully to understand what information is provided. 2. I look for relevant keywords or phrases that might give me a hint about the question being asked. The question asks about the number of public, private, and charter schools in Abu Dhabi. Let me see if I can find any relevant numbers in the context... 3. Ah-ha! I found it! The context mentions: * 218 public schools * 203 private schools * 22 charter schools Now, let's summarize what we have: * Public schools: 218 * Private schools: 203 * Charter schools: 22 So, the answer to the question is: * Public schools: 218 * Private schools: 203 * Charter schools: 22 I hope that answers your question! | F3: Okay, let's break this down step by step to answer the question. 1. **Identify the relevant information:** The context provides data about public, private, and charter schools in Abu Dhabi. 2. **Extract the number of public schools:** There are 218 public schools. 3. **Extract the number of private schools:** There are 203 private schools. 4. **Extract the number of charter schools:** Since 2019, 22 charter schools have been established. 5. **Combine the numbers:** * Public schools: 218 * Private schools: 203 * Charter schools: 22 **Answer:** There are 218 public schools, 203 private schools, and 22 charter schools in Abu Dhabi. | G3: There are 218 public schools, 203 private schools, and 22 charter schools in Abu Dhabi. | H3: ['There are 218 public schools with a student population of 119,261, 80 percent of which are \nUAE nationals. The remainder are non-native but have Arabic as their first language. Since 2019, \n22 charter schools have been established , serving over 30,000 predominately n ative students in a \nstudent-centric education model that provides innovative learning practices in a stimulating \nenvironment. Currently there are 203 private schools in Abu Dhabi with UAE nationals \naccounting for 29 percent of enrollment. The number of students attending private schools has \nbeen growing at a compound annual growth rate of 2.4 percent up to 2019. \nExhibit 1 shows the demographics for Abu Dhabi schools.', 'There are 218 public schools with a student population of 119,261, 80 percent of which are \nUAE nationals. The remainder are non-native but have Arabic as their first language. Since 2019, \n22 charter schools have been established , serving over 30,000 predominately n ative students in a \nstudent-centric education model that provides innovative learning practices in a stimulating \nenvironment. Currently there are 203 private schools in Abu Dhabi with UAE nationals \naccounting for 29 percent of enrollment. The number of students attending private schools has \nbeen growing at a compound annual growth rate of 2.4 percent up to 2019. \nExhibit 1 shows the demographics for Abu Dhabi schools.', 'There are 218 public schools with a student population of 119,261, 80 percent of which are \nUAE nationals. The remainder are non-native but have Arabic as their first language. Since 2019, \n22 charter schools have been established , serving over 30,000 predominately n ative students in a \nstudent-centric education model that provides innovative learning practices in a stimulating \nenvironment. Currently there are 203 private schools in Abu Dhabi with UAE nationals \naccounting for 29 percent of enrollment. The number of students attending private schools has \nbeen growing at a compound annual growth rate of 2.4 percent up to 2019. \nExhibit 1 shows the demographics for Abu Dhabi schools.', 'There are 218 public schools with a student population of 119,261, 80 percent of which are \nUAE nationals. The remainder are non-native but have Arabic as their first language. Since 2019, \n22 charter schools have been established , serving over 30,000 predominately n ative students in a \nstudent-centric education model that provides innovative learning practices in a stimulating \nenvironment. Currently there are 203 private schools in Abu Dhabi with UAE nationals \naccounting for 29 percent of enrollment. The number of students attending private schools has \nbeen growing at a compound annual growth rate of 2.4 percent up to 2019. \nExhibit 1 shows the demographics for Abu Dhabi schools.'] | I3: ['There are 218 public schools with a student population of 119,261, 80 percent of which are \nUAE nationals. The remainder are non-native but have Arabic as their first language. Since 2019, \n22 charter schools have been established , serving over 30,000 predominately n ative students in a \nstudent-centric education model that provides innovative learning practices in a stimulating \nenvironment. Currently there are 203 private schools in Abu Dhabi with UAE nationals \naccounting for 29 percent of enrollment. The number of students attending private schools has \nbeen growing at a compound annual growth rate of 2.4 percent up to 2019. \nExhibit 1 shows the demographics for Abu Dhabi schools.', 'There are 218 public schools with a student population of 119,261, 80 percent of which are \nUAE nationals. The remainder are non-native but have Arabic as their first language. Since 2019, \n22 charter schools have been established , serving over 30,000 predominately n ative students in a \nstudent-centric education model that provides innovative learning practices in a stimulating \nenvironment. Currently there are 203 private schools in Abu Dhabi with UAE nationals \naccounting for 29 percent of enrollment. The number of students attending private schools has \nbeen growing at a compound annual growth rate of 2.4 percent up to 2019. \nExhibit 1 shows the demographics for Abu Dhabi schools.', 'There are 218 public schools with a student population of 119,261, 80 percent of which are \nUAE nationals. The remainder are non-native but have Arabic as their first language. Since 2019, \n22 charter schools have been established , serving over 30,000 predominately n ative students in a \nstudent-centric education model that provides innovative learning practices in a stimulating \nenvironment. Currently there are 203 private schools in Abu Dhabi with UAE nationals \naccounting for 29 percent of enrollment. The number of students attending private schools has \nbeen growing at a compound annual growth rate of 2.4 percent up to 2019. \nExhibit 1 shows the demographics for Abu Dhabi schools.', 'There are 218 public schools with a student population of 119,261, 80 percent of which are \nUAE nationals. The remainder are non-native but have Arabic as their first language. Since 2019, \n22 charter schools have been established , serving over 30,000 predominately n ative students in a \nstudent-centric education model that provides innovative learning practices in a stimulating \nenvironment. Currently there are 203 private schools in Abu Dhabi with UAE nationals \naccounting for 29 percent of enrollment. The number of students attending private schools has \nbeen growing at a compound annual growth rate of 2.4 percent up to 2019. \nExhibit 1 shows the demographics for Abu Dhabi schools.'] | J3: ['There are 218 public schools with a student population of 119,261, 80 percent of which are \nUAE nationals. The remainder are non-native but have Arabic as their first language. Since 2019, \n22 charter schools have been established , serving over 30,000 predominately n ative students in a \nstudent-centric education model that provides innovative learning practices in a stimulating \nenvironment. Currently there are 203 private schools in Abu Dhabi with UAE nationals \naccounting for 29 percent of enrollment. The number of students attending private schools has \nbeen growing at a compound annual growth rate of 2.4 percent up to 2019. \nExhibit 1 shows the demographics for Abu Dhabi schools.', 'There are 218 public schools with a student population of 119,261, 80 percent of which are \nUAE nationals. The remainder are non-native but have Arabic as their first language. Since 2019, \n22 charter schools have been established , serving over 30,000 predominately n ative students in a \nstudent-centric education model that provides innovative learning practices in a stimulating \nenvironment. Currently there are 203 private schools in Abu Dhabi with UAE nationals \naccounting for 29 percent of enrollment. The number of students attending private schools has \nbeen growing at a compound annual growth rate of 2.4 percent up to 2019. \nExhibit 1 shows the demographics for Abu Dhabi schools.', 'There are 218 public schools with a student population of 119,261, 80 percent of which are \nUAE nationals. The remainder are non-native but have Arabic as their first language. Since 2019, \n22 charter schools have been established , serving over 30,000 predominately n ative students in a \nstudent-centric education model that provides innovative learning practices in a stimulating \nenvironment. Currently there are 203 private schools in Abu Dhabi with UAE nationals \naccounting for 29 percent of enrollment. The number of students attending private schools has \nbeen growing at a compound annual growth rate of 2.4 percent up to 2019. \nExhibit 1 shows the demographics for Abu Dhabi schools.', 'There are 218 public schools with a student population of 119,261, 80 percent of which are \nUAE nationals. The remainder are non-native but have Arabic as their first language. Since 2019, \n22 charter schools have been established , serving over 30,000 predominately n ative students in a \nstudent-centric education model that provides innovative learning practices in a stimulating \nenvironment. Currently there are 203 private schools in Abu Dhabi with UAE nationals \naccounting for 29 percent of enrollment. The number of students attending private schools has \nbeen growing at a compound annual growth rate of 2.4 percent up to 2019. \nExhibit 1 shows the demographics for Abu Dhabi schools.'] | K3: Based on the provided documents, the total number of public, private, and charter schools in Abu Dhabi is: * Public Schools: 218 * Private Schools: 203 * Charter Schools: 22 Therefore, the comprehensive final answer to the main question is: There are a total of **218 + 225 = 443** public, private, and charter schools in Abu Dhabi. | L3: Based on the provided information, there are a total of 441 schools operating in Abu Dhabi, comprised of three categories: 218 public schools, 203 private schools, and 22 charter schools. Therefore, Abu Dhabi has 218 public, 203 private, and 22 charter schools. | M3: There are **218** public schools, **203** private schools, and **22** charter schools in Abu Dhabi, making a total of **443** schools. | N3: There are 218 public schools with a student population of 119,261, 80 percent of which are UAE nationals. The remainder are non-native but have Arabic as their first language. Since 2019, 22 charter schools have been established , serving over 30,000 predominately n ative students in a student-centric education model that provides innovative learning practices in a stimulating environment. Currently there are 203 private schools in Abu Dhabi with UAE nationals accounting for 29 percent of enrollment. The number of students attending private schools has been growing at a compound annual growth rate of 2.4 percent up to 2019. Exhibit 1 shows the demographics for Abu Dhabi schools. There are 218 public schools with a student population of 119,261, 80 percent of which are UAE nationals. The remainder are non-native but have Arabic as their first language. Since 2019, 22 charter schools have been established , serving over 30,000 predominately n ative students in a student-centric education model that provides innovative learning practices in a stimulating environment. Currently there are 203 private schools in Abu Dhabi with UAE nationals accounting for 29 percent of enrollment. The number of students attending private schools has been growing at a compound annual growth rate of 2.4 percent up to 2019. Exhibit 1 shows the demographics for Abu Dhabi schools. There are 218 public schools with a student population of 119,261, 80 percent of which are UAE nationals. The remainder are non-native but have Arabic as their first language. Since 2019, 22 charter schools have been established , serving over 30,000 predominately n ative students in a student-centric education model that provides innovative learning practices in a stimulating environment. Currently there are 203 private schools in Abu Dhabi with UAE nationals accounting for 29 percent of enrollment. The number of students attending private schools has been growing at a compound annual growth rate of 2.4 percent up to 2019. Exhibit 1 shows the demographics for Abu Dhabi schools. There are 218 public schools with a student population of 119,261, 80 percent of which are UAE nationals. The remainder are non-native but have Arabic as their first language. Since 2019, 22 charter schools have been established , serving over 30,000 predominately n ative students in a student-centric education model that provides innovative learning practices in a stimulating environment. Currently there are 203 private schools in Abu Dhabi with UAE nationals accounting for 29 percent of enrollment. The number of students attending private schools has been growing at a compound annual growth rate of 2.4 percent up to 2019. Exhibit 1 shows the demographics for Abu Dhabi schools. There are 218 public schools with a student population of 119,261, 80 percent of which are UAE nationals. The remainder are non-native but have Arabic as their first language. Since 2019, 22 charter schools have been established , serving over 30,000 predominately n ative students in a student-centric education model that provides innovative learning practices in a stimulating environment. Currently there are 203 private schools in Abu Dhabi with UAE nationals accounting for 29 percent of enrollment. The number of students attending private schools has been growing at a compound annual growth rate of 2.4 percent up to 2019. Exhibit 1 shows the demographics for Abu Dhabi schools. There are 218 public schools with a student population of 119,261, 80 percent of which are UAE nationals. The remainder are non-native but have Arabic as their first language. Since 2019, 22 charter schools have been established , serving over 30,000 predominately n ative students in a student-centric education model that provides innovative learning practices in a stimulating environment. Currently there are 203 private schools in Abu Dhabi with UAE nationals accounting for 29 percent of enrollment. The number of students attending private schools has been growing at a compound annual growth rate of 2.4 percent up to 2019. Exhibit 1 shows the demographics for Abu Dhabi schools. There are 218 public schools with a student population of 119,261, 80 percent of which are UAE nationals. The remainder are non-native but have Arabic as their first language. Since 2019, 22 charter schools have been established , serving over 30,000 predominately n ative students in a student-centric education model that provides innovative learning practices in a stimulating environment. Currently there are 203 private schools in Abu Dhabi with UAE nationals accounting for 29 percent of enrollment. The number of students attending private schools has been growing at a compound annual growth rate of 2.4 percent up to 2019. Exhibit 1 shows the demographics for Abu Dhabi schools. There are 218 public schools with a student population of 119,261, 80 percent of which are UAE nationals. The remainder are non-native but have Arabic as their first language. Since 2019, 22 charter schools have been established , serving over 30,000 predominately n ative students in a student-centric education model that provides innovative learning practices in a stimulating environment. Currently there are 203 private schools in Abu Dhabi with UAE nationals accounting for 29 percent of enrollment. The number of students attending private schools has been growing at a compound annual growth rate of 2.4 percent up to 2019. Exhibit 1 shows the demographics for Abu Dhabi schools. There are 218 public schools with a student population of 119,261, 80 percent of which are UAE nationals. The remainder are non-native but have Arabic as their first language. Since 2019, 22 charter schools have been established , serving over 30,000 predominately n ative students in a student-centric education model that provides innovative learning practices in a stimulating environment. Currently there are 203 private schools in Abu Dhabi with UAE nationals accounting for 29 percent of enrollment. The number of students attending private schools has been growing at a compound annual growth rate of 2.4 percent up to 2019. Exhibit 1 shows the demographics for Abu Dhabi schools. There are 218 public schools with a student population of 119,261, 80 percent of which are UAE nationals. The remainder are non-native but have Arabic as their first language. Since 2019, 22 charter schools have been established , serving over 30,000 predominately n ative students in a student-centric education model that provides innovative learning practices in a stimulating environment. Currently there are 203 private schools in Abu Dhabi with UAE nationals accounting for 29 percent of enrollment. The number of students attending private schools has been growing at a compound annual growth rate of 2.4 percent up to 2019. Exhibit 1 shows the demographics for Abu Dhabi schools. There are 218 public schools with a student population of 119,261, 80 percent of which are UAE nationals. The remainder are non-native but have Arabic as their first language. Since 2019, 22 charter schools have been established , serving over 30,000 predominately n ative students in a student-centric education model that provides innovative learning practices in a stimulating environment. Currently there are 203 private schools in Abu Dhabi with UAE nationals accounting for 29 percent of enrollment. The number of students attending private schools has been growing at a compound annual growth rate of 2.4 percent up to 2019. Exhibit 1 shows the demographics for Abu Dhabi schools. There are 218 public schools with a student population of 119,261, 80 percent of which are UAE nationals. The remainder are non-native but have Arabic as their first language. Since 2019, 22 charter schools have been established , serving over 30,000 predominately n ative students in a student-centric education model that provides innovative learning practices in a stimulating environment. Currently there are 203 private schools in Abu Dhabi with UAE nationals accounting for 29 percent of enrollment. The number of students attending private schools has been growing at a compound annual growth rate of 2.4 percent up to 2019. Exhibit 1 shows the demographics for Abu Dhabi schools. | O3: ['There are 218 public schools with a student population of 119,261, 80 percent of which are \nUAE nationals. The remainder are non-native but have Arabic as their first language. Since 2019, \n22 charter schools have been established , serving over 30,000 predominately n ative students in a \nstudent-centric education model that provides innovative learning practices in a stimulating \nenvironment. Currently there are 203 private schools in Abu Dhabi with UAE nationals \naccounting for 29 percent of enrollment. The number of students attending private schools has \nbeen growing at a compound annual growth rate of 2.4 percent up to 2019. \nExhibit 1 shows the demographics for Abu Dhabi schools.\n\nThere are 218 public schools with a student population of 119,261, 80 percent of which are \nUAE nationals. The remainder are non-native but have Arabic as their first language. Since 2019, \n22 charter schools have been established , serving over 30,000 predominately n ative students in a \nstudent-centric education model that provides innovative learning practices in a stimulating \nenvironment. Currently there are 203 private schools in Abu Dhabi with UAE nationals \naccounting for 29 percent of enrollment. The number of students attending private schools has \nbeen growing at a compound annual growth rate of 2.4 percent up to 2019. \nExhibit 1 shows the demographics for Abu Dhabi schools.\n\nThere are 218 public schools with a student population of 119,261, 80 percent of which are \nUAE nationals. The remainder are non-native but have Arabic as their first language. Since 2019, \n22 charter schools have been established , serving over 30,000 predominately n ative students in a \nstudent-centric education model that provides innovative learning practices in a stimulating \nenvironment. Currently there are 203 private schools in Abu Dhabi with UAE nationals \naccounting for 29 percent of enrollment. The number of students attending private schools has \nbeen growing at a compound annual growth rate of 2.4 percent up to 2019. \nExhibit 1 shows the demographics for Abu Dhabi schools.\n\nThere are 218 public schools with a student population of 119,261, 80 percent of which are \nUAE nationals. The remainder are non-native but have Arabic as their first language. Since 2019, \n22 charter schools have been established , serving over 30,000 predominately n ative students in a \nstudent-centric education model that provides innovative learning practices in a stimulating \nenvironment. Currently there are 203 private schools in Abu Dhabi with UAE nationals \naccounting for 29 percent of enrollment. The number of students attending private schools has \nbeen growing at a compound annual growth rate of 2.4 percent up to 2019. \nExhibit 1 shows the demographics for Abu Dhabi schools.\n\nThere are 218 public schools with a student population of 119,261, 80 percent of which are \nUAE nationals. The remainder are non-native but have Arabic as their first language. Since 2019, \n22 charter schools have been established , serving over 30,000 predominately n ative students in a \nstudent-centric education model that provides innovative learning practices in a stimulating \nenvironment. Currently there are 203 private schools in Abu Dhabi with UAE nationals \naccounting for 29 percent of enrollment. The number of students attending private schools has \nbeen growing at a compound annual growth rate of 2.4 percent up to 2019. \nExhibit 1 shows the demographics for Abu Dhabi schools.\n\nThere are 218 public schools with a student population of 119,261, 80 percent of which are \nUAE nationals. The remainder are non-native but have Arabic as their first language. Since 2019, \n22 charter schools have been established , serving over 30,000 predominately n ative students in a \nstudent-centric education model that provides innovative learning practices in a stimulating \nenvironment. Currently there are 203 private schools in Abu Dhabi with UAE nationals \naccounting for 29 percent of enrollment. The number of students attending private schools has \nbeen growing at a compound annual growth rate of 2.4 percent up to 2019. \nExhibit 1 shows the demographics for Abu Dhabi schools.\n\nThere are 218 public schools with a student population of 119,261, 80 percent of which are \nUAE nationals. The remainder are non-native but have Arabic as their first language. Since 2019, \n22 charter schools have been established , serving over 30,000 predominately n ative students in a \nstudent-centric education model that provides innovative learning practices in a stimulating \nenvironment. Currently there are 203 private schools in Abu Dhabi with UAE nationals \naccounting for 29 percent of enrollment. The number of students attending private schools has \nbeen growing at a compound annual growth rate of 2.4 percent up to 2019. \nExhibit 1 shows the demographics for Abu Dhabi schools.\n\nThere are 218 public schools with a student population of 119,261, 80 percent of which are \nUAE nationals. The remainder are non-native but have Arabic as their first language. Since 2019, \n22 charter schools have been established , serving over 30,000 predominately n ative students in a \nstudent-centric education model that provides innovative learning practices in a stimulating \nenvironment. Currently there are 203 private schools in Abu Dhabi with UAE nationals \naccounting for 29 percent of enrollment. The number of students attending private schools has \nbeen growing at a compound annual growth rate of 2.4 percent up to 2019. \nExhibit 1 shows the demographics for Abu Dhabi schools.\n\nThere are 218 public schools with a student population of 119,261, 80 percent of which are \nUAE nationals. The remainder are non-native but have Arabic as their first language. Since 2019, \n22 charter schools have been established , serving over 30,000 predominately n ative students in a \nstudent-centric education model that provides innovative learning practices in a stimulating \nenvironment. Currently there are 203 private schools in Abu Dhabi with UAE nationals \naccounting for 29 percent of enrollment. The number of students attending private schools has \nbeen growing at a compound annual growth rate of 2.4 percent up to 2019. \nExhibit 1 shows the demographics for Abu Dhabi schools.\n\nThere are 218 public schools with a student population of 119,261, 80 percent of which are \nUAE nationals. The remainder are non-native but have Arabic as their first language. Since 2019, \n22 charter schools have been established , serving over 30,000 predominately n ative students in a \nstudent-centric education model that provides innovative learning practices in a stimulating \nenvironment. Currently there are 203 private schools in Abu Dhabi with UAE nationals \naccounting for 29 percent of enrollment. The number of students attending private schools has \nbeen growing at a compound annual growth rate of 2.4 percent up to 2019. \nExhibit 1 shows the demographics for Abu Dhabi schools.\n\nThere are 218 public schools with a student population of 119,261, 80 percent of which are \nUAE nationals. The remainder are non-native but have Arabic as their first language. Since 2019, \n22 charter schools have been established , serving over 30,000 predominately n ative students in a \nstudent-centric education model that provides innovative learning practices in a stimulating \nenvironment. Currently there are 203 private schools in Abu Dhabi with UAE nationals \naccounting for 29 percent of enrollment. The number of students attending private schools has \nbeen growing at a compound annual growth rate of 2.4 percent up to 2019. \nExhibit 1 shows the demographics for Abu Dhabi schools.\n\nThere are 218 public schools with a student population of 119,261, 80 percent of which are \nUAE nationals. The remainder are non-native but have Arabic as their first language. Since 2019, \n22 charter schools have been established , serving over 30,000 predominately n ative students in a \nstudent-centric education model that provides innovative learning practices in a stimulating \nenvironment. Currently there are 203 private schools in Abu Dhabi with UAE nationals \naccounting for 29 percent of enrollment. The number of students attending private schools has \nbeen growing at a compound annual growth rate of 2.4 percent up to 2019. \nExhibit 1 shows the demographics for Abu Dhabi schools.'] | P3: ['There are 218 public schools with a student population of 119,261, 80 percent of which are \nUAE nationals. The remainder are non-native but have Arabic as their first language. Since 2019, \n22 charter schools have been established , serving over 30,000 predominately n ative students in a \nstudent-centric education model that provides innovative learning practices in a stimulating \nenvironment. Currently there are 203 private schools in Abu Dhabi with UAE nationals \naccounting for 29 percent of enrollment. The number of students attending private schools has \nbeen growing at a compound annual growth rate of 2.4 percent up to 2019. \nExhibit 1 shows the demographics for Abu Dhabi schools.\n\nThere are 218 public schools with a student population of 119,261, 80 percent of which are \nUAE nationals. The remainder are non-native but have Arabic as their first language. Since 2019, \n22 charter schools have been established , serving over 30,000 predominately n ative students in a \nstudent-centric education model that provides innovative learning practices in a stimulating \nenvironment. Currently there are 203 private schools in Abu Dhabi with UAE nationals \naccounting for 29 percent of enrollment. The number of students attending private schools has \nbeen growing at a compound annual growth rate of 2.4 percent up to 2019. \nExhibit 1 shows the demographics for Abu Dhabi schools.\n\nThere are 218 public schools with a student population of 119,261, 80 percent of which are \nUAE nationals. The remainder are non-native but have Arabic as their first language. Since 2019, \n22 charter schools have been established , serving over 30,000 predominately n ative students in a \nstudent-centric education model that provides innovative learning practices in a stimulating \nenvironment. Currently there are 203 private schools in Abu Dhabi with UAE nationals \naccounting for 29 percent of enrollment. The number of students attending private schools has \nbeen growing at a compound annual growth rate of 2.4 percent up to 2019. \nExhibit 1 shows the demographics for Abu Dhabi schools.\n\nThere are 218 public schools with a student population of 119,261, 80 percent of which are \nUAE nationals. The remainder are non-native but have Arabic as their first language. Since 2019, \n22 charter schools have been established , serving over 30,000 predominately n ative students in a \nstudent-centric education model that provides innovative learning practices in a stimulating \nenvironment. Currently there are 203 private schools in Abu Dhabi with UAE nationals \naccounting for 29 percent of enrollment. The number of students attending private schools has \nbeen growing at a compound annual growth rate of 2.4 percent up to 2019. \nExhibit 1 shows the demographics for Abu Dhabi schools.\n\nThere are 218 public schools with a student population of 119,261, 80 percent of which are \nUAE nationals. The remainder are non-native but have Arabic as their first language. Since 2019, \n22 charter schools have been established , serving over 30,000 predominately n ative students in a \nstudent-centric education model that provides innovative learning practices in a stimulating \nenvironment. Currently there are 203 private schools in Abu Dhabi with UAE nationals \naccounting for 29 percent of enrollment. The number of students attending private schools has \nbeen growing at a compound annual growth rate of 2.4 percent up to 2019. \nExhibit 1 shows the demographics for Abu Dhabi schools.\n\nThere are 218 public schools with a student population of 119,261, 80 percent of which are \nUAE nationals. The remainder are non-native but have Arabic as their first language. Since 2019, \n22 charter schools have been established , serving over 30,000 predominately n ative students in a \nstudent-centric education model that provides innovative learning practices in a stimulating \nenvironment. Currently there are 203 private schools in Abu Dhabi with UAE nationals \naccounting for 29 percent of enrollment. The number of students attending private schools has \nbeen growing at a compound annual growth rate of 2.4 percent up to 2019. \nExhibit 1 shows the demographics for Abu Dhabi schools.\n\nThere are 218 public schools with a student population of 119,261, 80 percent of which are \nUAE nationals. The remainder are non-native but have Arabic as their first language. Since 2019, \n22 charter schools have been established , serving over 30,000 predominately n ative students in a \nstudent-centric education model that provides innovative learning practices in a stimulating \nenvironment. Currently there are 203 private schools in Abu Dhabi with UAE nationals \naccounting for 29 percent of enrollment. The number of students attending private schools has \nbeen growing at a compound annual growth rate of 2.4 percent up to 2019. \nExhibit 1 shows the demographics for Abu Dhabi schools.\n\nThere are 218 public schools with a student population of 119,261, 80 percent of which are \nUAE nationals. The remainder are non-native but have Arabic as their first language. Since 2019, \n22 charter schools have been established , serving over 30,000 predominately n ative students in a \nstudent-centric education model that provides innovative learning practices in a stimulating \nenvironment. Currently there are 203 private schools in Abu Dhabi with UAE nationals \naccounting for 29 percent of enrollment. The number of students attending private schools has \nbeen growing at a compound annual growth rate of 2.4 percent up to 2019. \nExhibit 1 shows the demographics for Abu Dhabi schools.\n\nThere are 218 public schools with a student population of 119,261, 80 percent of which are \nUAE nationals. The remainder are non-native but have Arabic as their first language. Since 2019, \n22 charter schools have been established , serving over 30,000 predominately n ative students in a \nstudent-centric education model that provides innovative learning practices in a stimulating \nenvironment. Currently there are 203 private schools in Abu Dhabi with UAE nationals \naccounting for 29 percent of enrollment. The number of students attending private schools has \nbeen growing at a compound annual growth rate of 2.4 percent up to 2019. \nExhibit 1 shows the demographics for Abu Dhabi schools.\n\nThere are 218 public schools with a student population of 119,261, 80 percent of which are \nUAE nationals. The remainder are non-native but have Arabic as their first language. Since 2019, \n22 charter schools have been established , serving over 30,000 predominately n ative students in a \nstudent-centric education model that provides innovative learning practices in a stimulating \nenvironment. Currently there are 203 private schools in Abu Dhabi with UAE nationals \naccounting for 29 percent of enrollment. The number of students attending private schools has \nbeen growing at a compound annual growth rate of 2.4 percent up to 2019. \nExhibit 1 shows the demographics for Abu Dhabi schools.\n\nThere are 218 public schools with a student population of 119,261, 80 percent of which are \nUAE nationals. The remainder are non-native but have Arabic as their first language. Since 2019, \n22 charter schools have been established , serving over 30,000 predominately n ative students in a \nstudent-centric education model that provides innovative learning practices in a stimulating \nenvironment. Currently there are 203 private schools in Abu Dhabi with UAE nationals \naccounting for 29 percent of enrollment. The number of students attending private schools has \nbeen growing at a compound annual growth rate of 2.4 percent up to 2019. \nExhibit 1 shows the demographics for Abu Dhabi schools.\n\nThere are 218 public schools with a student population of 119,261, 80 percent of which are \nUAE nationals. The remainder are non-native but have Arabic as their first language. Since 2019, \n22 charter schools have been established , serving over 30,000 predominately n ative students in a \nstudent-centric education model that provides innovative learning practices in a stimulating \nenvironment. Currently there are 203 private schools in Abu Dhabi with UAE nationals \naccounting for 29 percent of enrollment. The number of students attending private schools has \nbeen growing at a compound annual growth rate of 2.4 percent up to 2019. \nExhibit 1 shows the demographics for Abu Dhabi schools.'] | Q3: 1 | R3: The score is 1.00 because the first node contains all required information and there are no irrelevant nodes ranked higher; thus the score cannot exceed 1. The node’s reason states: "The context explicitly states the numbers needed for the answer: 'There are 218 public schools' and 'Currently there are 203 private schools' and '22 charter schools have been established'." | S3: 1 | T3: The score is 1.00 because the sentence in the expected output directly matches the information in node 1 of the retrieval context, confirming all school counts. | U3: 1 | V3: The score is 1.00 because the actual output perfectly aligns with the retrieval context—no contradictions were found, indicating complete faithfulness! | W3: 1 | X3: The response correctly states the three key figures—218 public schools, 203 private schools, and 22 charter schools—matching the expected output exactly. It includes no contradictory information and covers all required points, merely adding explanatory context. This satisfies all evaluation steps, warranting a perfect score. | Y3: 1 | Z3: The score is 1.00 because the only node in the retrieval contexts is ranked first and contains the exact numbers needed for the answer: "There are 218 public schools" and "Currently there are 203 private schools" and "22 charter schools have been established". With no irrelevant nodes to outrank it, the precision cannot exceed 1, and it is already perfect. | AA3: 1 | AB3: The score is 1.00 because the sentence in the expected output directly matches the information in node 1 of the retrieval context, confirming all school counts. | AC3: 1 | AD3: The score is 1.00 because there are no contradictions, indicating the actual output perfectly aligns with the retrieval context! | AE3: 1 | AF3: The response accurately states the numbers for public, private, and charter schools, matching the expected facts and including all key points. The phrasing is equivalent and no contradictions are present. | AG3: 1 | AH3: The score is 1.00 because the first node contains all required information and there are no irrelevant nodes ranked higher; thus the score cannot exceed 1. The node’s reason states: "The context explicitly states the numbers needed for the answer: 'There are 218 public schools' and 'Currently there are 203 private schools' and '22 charter schools have been established'." | AI3: 1 | AJ3: The score is 1.00 because the sentence in the expected output directly matches the information in node 1 of the retrieval context, confirming all school counts. | AK3: 1 | AL3: The score is 1.00 because the actual output perfectly aligns with the retrieval context—no contradictions were found, indicating complete faithfulness! | AM3: 1 | AN3: The actual output matches the expected output in all factual details—218 public, 203 private, and 22 charter schools in Abu Dhabi—without any contradictions or omissions, and it paraphrases the expected statement correctly. | AO3: 1 | AP3: The score is 1.00 because the single node ranked first contains the exact numbers for public, private, and charter schools in Abu Dhabi, ensuring all relevant information is prioritized and no irrelevant nodes are interleaved. The node’s reason states: "The context explicitly states the numbers needed for the answer: 'There are 218 public schools' and 'Currently there are 203 private schools' and '22 charter schools have been established'." | AQ3: 1 | AR3: The score is 1.00 because the sentence in the expected output directly matches the information in node 1 of the retrieval context, confirming all school counts. | AS3: 1 | AT3: The score is 1.00 because there are no contradictions, indicating the output perfectly aligns with the retrieval context! | AU3: 0.2 | AV3: The actual output contradicts the expected data by using 225 instead of 203 for private schools and incorrectly summing the totals. It also omits the correct private school count in the final statement, missing a key point from the expected output. These errors violate the factual comparison and completeness criteria, resulting in a low score. | AW3: 1 | AX3: The score is 1.00 because the only node (rank 1) contains the exact numbers needed, as stated: "The context states \"There are 218 public schools…\" and \"Currently there are 203 private schools…\" and \"Since 2019, 22 charter schools have been established…\", which directly provide the numbers required in the expected output." All relevant information is ranked above any irrelevant nodes. | AY3: 1 | AZ3: The score is 1.00 because the node(s) in retrieval context contain the exact phrase "218 public schools, 203 private schools, and 22 charter schools," which directly matches the expected sentence. | BA3: 0.66666667 | BB3: The score is 0.67 because the actual output incorrectly states 441 schools, while the retrieval context shows 218 public, 203 private, and 22 charter schools, totaling 443 schools. | BC3: 1 | BD3: The response correctly lists the same numbers for public, private, and charter schools as the expected output, and it does not contradict any of those facts. All key points from the expected output are present, and the additional context about the total number of schools is supplementary rather than conflicting. Thus the answer meets all evaluation criteria and receives a perfect score. | BE3: 1 | BF3: The score is 1.00 because the only node (rank 1) contains the exact numbers needed, as stated: "The context states \"There are 218 public schools…\" and \"Currently there are 203 private schools…\" and \"Since 2019, 22 charter schools have been established…\", which directly provide the numbers required in the expected output." All relevant information is ranked above any irrelevant nodes. | BG3: 1 | BH3: The score is 1.00 because the node(s) in retrieval context contain the exact phrase "218 public schools, 203 private schools, and 22 charter schools," which directly matches the expected sentence. | BI3: 1 | BJ3: The score is 1.00 because there are no contradictions, indicating the actual output perfectly aligns with the retrieval context! | BK3: 1 | BL3: The actual output correctly lists the same numbers of public, private, and charter schools as the expected output, with no contradictions. All key points are present, and the additional total of 443 schools is extra information that does not conflict. The content is semantically equivalent to the expected answer. | BM3: synthetic
A4: 5 | B4: What mandatory early education requirement must Austrian children complete before entering primary school? | C4: Austrian children must complete one compulsory year of Kindergarten at age 5 before beginning primary school. | D4: Since 2010, one year of Kindergarten has been compulsory for all children age 5 before they start attending primary school in Volksschule at age 6. | E4: To answer this question, I will follow my thought process step by step. Step 1: Identify relevant information in the context. The context mentions "children whose sixth birthday falls before March 1 in the following calendar year may request earlier admission provided that the child is mature enough and has the required social competency to attend school." Step 2: Analyze the given condition. The condition states that children can request earlier admission if they are mature enough and have the required social competency. This implies that there might be some requirement or stage before entering primary school. Step 3: Look for relevant information in the context. In the context, it is mentioned that "Six -year-old children considered insufficiently mature to attend school must attend preschool." This suggests that there might be an early education requirement for six-year-old children who are not deemed mature enough for primary school. Conclusion: Based on the given condition and information in the context, I deduce that Austrian children must complete preschool education before entering primary school. | F4: Okay, let's break this down step by step to answer the question. 1. **Understand the question:** The question asks about a mandatory early education requirement for Austrian children before they enter primary school. 2. **Scan the context:** I need to read the provided text carefully to find the information related to this question. 3. **Identify relevant information:** The text states: "Six -year-old children considered insufficiently mature to attend school must attend preschool." 4. **Formulate the answer:** Based on the information identified, the answer is that six-year-old children considered insufficiently mature to attend school must attend preschool. Therefore, my answer is: Six -year-old children considered insufficiently mature to attend school must attend preschool. | G4: The mandatory early education requirement before entering primary school is that six-year-old children considered **insufficiently mature** to attend school must attend **preschool**. | H4: ['of children whose sixth birthday falls before March 1 in the following calendar year may request \nearlier admission provided that the child is mature enough and has the required social competency \nto attend school. Six -year-old children considered insufficiently mature to attend school must \nattend preschool. Primary school comprises primary level I (preschool stage where r equired, and \nGrades 1 and 2) and primary level II ( Grades 3 and 4). At the lower secondary level (Grades 5 to \n8), students ages 10 to 14 can apply for entry to a lower level academic secondary school (Allgemein \nbildende höhere Schule—Unterstufe) or a compulsory secondary school (Mittelschule). \nA\nustria has reformed lower secondary education (UNESCO ʼs International Standard \nClassification of Education [ ISCED] Level 2) to reduce the effects of streaming students into \ndifferent educational tracks too earl y.1 The Austrian government introduced the compulsory', 'of children whose sixth birthday falls before March 1 in the following calendar year may request \nearlier admission provided that the child is mature enough and has the required social competency \nto attend school. Six -year-old children considered insufficiently mature to attend school must \nattend preschool. Primary school comprises primary level I (preschool stage where r equired, and \nGrades 1 and 2) and primary level II ( Grades 3 and 4). At the lower secondary level (Grades 5 to \n8), students ages 10 to 14 can apply for entry to a lower level academic secondary school (Allgemein \nbildende höhere Schule—Unterstufe) or a compulsory secondary school (Mittelschule). \nA\nustria has reformed lower secondary education (UNESCO ʼs International Standard \nClassification of Education [ ISCED] Level 2) to reduce the effects of streaming students into \ndifferent educational tracks too earl y.1 The Austrian government introduced the compulsory', 'of children whose sixth birthday falls before March 1 in the following calendar year may request \nearlier admission provided that the child is mature enough and has the required social competency \nto attend school. Six -year-old children considered insufficiently mature to attend school must \nattend preschool. Primary school comprises primary level I (preschool stage where r equired, and \nGrades 1 and 2) and primary level II ( Grades 3 and 4). At the lower secondary level (Grades 5 to \n8), students ages 10 to 14 can apply for entry to a lower level academic secondary school (Allgemein \nbildende höhere Schule—Unterstufe) or a compulsory secondary school (Mittelschule). \nA\nustria has reformed lower secondary education (UNESCO ʼs International Standard \nClassification of Education [ ISCED] Level 2) to reduce the effects of streaming students into \ndifferent educational tracks too earl y.1 The Austrian government introduced the compulsory', 'of children whose sixth birthday falls before March 1 in the following calendar year may request \nearlier admission provided that the child is mature enough and has the required social competency \nto attend school. Six -year-old children considered insufficiently mature to attend school must \nattend preschool. Primary school comprises primary level I (preschool stage where r equired, and \nGrades 1 and 2) and primary level II ( Grades 3 and 4). At the lower secondary level (Grades 5 to \n8), students ages 10 to 14 can apply for entry to a lower level academic secondary school (Allgemein \nbildende höhere Schule—Unterstufe) or a compulsory secondary school (Mittelschule). \nA\nustria has reformed lower secondary education (UNESCO ʼs International Standard \nClassification of Education [ ISCED] Level 2) to reduce the effects of streaming students into \ndifferent educational tracks too earl y.1 The Austrian government introduced the compulsory'] | I4: ['of children whose sixth birthday falls before March 1 in the following calendar year may request \nearlier admission provided that the child is mature enough and has the required social competency \nto attend school. Six -year-old children considered insufficiently mature to attend school must \nattend preschool. Primary school comprises primary level I (preschool stage where r equired, and \nGrades 1 and 2) and primary level II ( Grades 3 and 4). At the lower secondary level (Grades 5 to \n8), students ages 10 to 14 can apply for entry to a lower level academic secondary school (Allgemein \nbildende höhere Schule—Unterstufe) or a compulsory secondary school (Mittelschule). \nA\nustria has reformed lower secondary education (UNESCO ʼs International Standard \nClassification of Education [ ISCED] Level 2) to reduce the effects of streaming students into \ndifferent educational tracks too earl y.1 The Austrian government introduced the compulsory', 'of children whose sixth birthday falls before March 1 in the following calendar year may request \nearlier admission provided that the child is mature enough and has the required social competency \nto attend school. Six -year-old children considered insufficiently mature to attend school must \nattend preschool. Primary school comprises primary level I (preschool stage where r equired, and \nGrades 1 and 2) and primary level II ( Grades 3 and 4). At the lower secondary level (Grades 5 to \n8), students ages 10 to 14 can apply for entry to a lower level academic secondary school (Allgemein \nbildende höhere Schule—Unterstufe) or a compulsory secondary school (Mittelschule). \nA\nustria has reformed lower secondary education (UNESCO ʼs International Standard \nClassification of Education [ ISCED] Level 2) to reduce the effects of streaming students into \ndifferent educational tracks too earl y.1 The Austrian government introduced the compulsory', 'of children whose sixth birthday falls before March 1 in the following calendar year may request \nearlier admission provided that the child is mature enough and has the required social competency \nto attend school. Six -year-old children considered insufficiently mature to attend school must \nattend preschool. Primary school comprises primary level I (preschool stage where r equired, and \nGrades 1 and 2) and primary level II ( Grades 3 and 4). At the lower secondary level (Grades 5 to \n8), students ages 10 to 14 can apply for entry to a lower level academic secondary school (Allgemein \nbildende höhere Schule—Unterstufe) or a compulsory secondary school (Mittelschule). \nA\nustria has reformed lower secondary education (UNESCO ʼs International Standard \nClassification of Education [ ISCED] Level 2) to reduce the effects of streaming students into \ndifferent educational tracks too earl y.1 The Austrian government introduced the compulsory', 'of children whose sixth birthday falls before March 1 in the following calendar year may request \nearlier admission provided that the child is mature enough and has the required social competency \nto attend school. Six -year-old children considered insufficiently mature to attend school must \nattend preschool. Primary school comprises primary level I (preschool stage where r equired, and \nGrades 1 and 2) and primary level II ( Grades 3 and 4). At the lower secondary level (Grades 5 to \n8), students ages 10 to 14 can apply for entry to a lower level academic secondary school (Allgemein \nbildende höhere Schule—Unterstufe) or a compulsory secondary school (Mittelschule). \nA\nustria has reformed lower secondary education (UNESCO ʼs International Standard \nClassification of Education [ ISCED] Level 2) to reduce the effects of streaming students into \ndifferent educational tracks too earl y.1 The Austrian government introduced the compulsory'] | J4: ['of children whose sixth birthday falls before March 1 in the following calendar year may request \nearlier admission provided that the child is mature enough and has the required social competency \nto attend school. Six -year-old children considered insufficiently mature to attend school must \nattend preschool. Primary school comprises primary level I (preschool stage where r equired, and \nGrades 1 and 2) and primary level II ( Grades 3 and 4). At the lower secondary level (Grades 5 to \n8), students ages 10 to 14 can apply for entry to a lower level academic secondary school (Allgemein \nbildende höhere Schule—Unterstufe) or a compulsory secondary school (Mittelschule). \nA\nustria has reformed lower secondary education (UNESCO ʼs International Standard \nClassification of Education [ ISCED] Level 2) to reduce the effects of streaming students into \ndifferent educational tracks too earl y.1 The Austrian government introduced the compulsory', 'of children whose sixth birthday falls before March 1 in the following calendar year may request \nearlier admission provided that the child is mature enough and has the required social competency \nto attend school. Six -year-old children considered insufficiently mature to attend school must \nattend preschool. Primary school comprises primary level I (preschool stage where r equired, and \nGrades 1 and 2) and primary level II ( Grades 3 and 4). At the lower secondary level (Grades 5 to \n8), students ages 10 to 14 can apply for entry to a lower level academic secondary school (Allgemein \nbildende höhere Schule—Unterstufe) or a compulsory secondary school (Mittelschule). \nA\nustria has reformed lower secondary education (UNESCO ʼs International Standard \nClassification of Education [ ISCED] Level 2) to reduce the effects of streaming students into \ndifferent educational tracks too earl y.1 The Austrian government introduced the compulsory', 'of children whose sixth birthday falls before March 1 in the following calendar year may request \nearlier admission provided that the child is mature enough and has the required social competency \nto attend school. Six -year-old children considered insufficiently mature to attend school must \nattend preschool. Primary school comprises primary level I (preschool stage where r equired, and \nGrades 1 and 2) and primary level II ( Grades 3 and 4). At the lower secondary level (Grades 5 to \n8), students ages 10 to 14 can apply for entry to a lower level academic secondary school (Allgemein \nbildende höhere Schule—Unterstufe) or a compulsory secondary school (Mittelschule). \nA\nustria has reformed lower secondary education (UNESCO ʼs International Standard \nClassification of Education [ ISCED] Level 2) to reduce the effects of streaming students into \ndifferent educational tracks too earl y.1 The Austrian government introduced the compulsory', 'of children whose sixth birthday falls before March 1 in the following calendar year may request \nearlier admission provided that the child is mature enough and has the required social competency \nto attend school. Six -year-old children considered insufficiently mature to attend school must \nattend preschool. Primary school comprises primary level I (preschool stage where r equired, and \nGrades 1 and 2) and primary level II ( Grades 3 and 4). At the lower secondary level (Grades 5 to \n8), students ages 10 to 14 can apply for entry to a lower level academic secondary school (Allgemein \nbildende höhere Schule—Unterstufe) or a compulsory secondary school (Mittelschule). \nA\nustria has reformed lower secondary education (UNESCO ʼs International Standard \nClassification of Education [ ISCED] Level 2) to reduce the effects of streaming students into \ndifferent educational tracks too earl y.1 The Austrian government introduced the compulsory'] | K4: In Austria, there is no specific age or year required for mandatory early education before entering primary school. However, Austrian children typically attend preschool (Vorschule) until they are considered mature enough and socially competent to enter primary school. The main requirement for primary school entry is that the child's sixth birthday must fall before March 1 of the following calendar year. If deemed insufficiently mature, a six-year-old can still attend preschool instead of primary school. | L4: Austrian children who fall before March 1st of the following calendar year must complete a mandatory early education program before entering primary school (Level I). This program is integrated within the primary level and is required for six-year-olds deemed insufficiently mature. To qualify for earlier admission, children must demonstrate both maturity and sufficient social competency. The specific duration of this preschool requirement is not defined in the provided documents. | M4: The mandatory early education requirement for Austrian children before entering primary school is to begin compulsory schooling. This starts at age seven (children whose 6th birthday is on or after March 1st of the school year). Children born before March 1st may enter primary school earlier if deemed mature and socially competent, but this is not mandatory. | N4: of children whose sixth birthday falls before March 1 in the following calendar year may request earlier admission provided that the child is mature enough and has the required social competency to attend school. Six -year-old children considered insufficiently mature to attend school must attend preschool. Primary school comprises primary level I (preschool stage where r equired, and Grades 1 and 2) and primary level II ( Grades 3 and 4). At the lower secondary level (Grades 5 to 8), students ages 10 to 14 can apply for entry to a lower level academic secondary school (Allgemein bildende höhere Schule—Unterstufe) or a compulsory secondary school (Mittelschule). A ustria has reformed lower secondary education (UNESCO ʼs International Standard Classification of Education [ ISCED] Level 2) to reduce the effects of streaming students into different educational tracks too earl y.1 The Austrian government introduced the compulsory of children whose sixth birthday falls before March 1 in the following calendar year may request earlier admission provided that the child is mature enough and has the required social competency to attend school. Six -year-old children considered insufficiently mature to attend school must attend preschool. Primary school comprises primary level I (preschool stage where r equired, and Grades 1 and 2) and primary level II ( Grades 3 and 4). At the lower secondary level (Grades 5 to 8), students ages 10 to 14 can apply for entry to a lower level academic secondary school (Allgemein bildende höhere Schule—Unterstufe) or a compulsory secondary school (Mittelschule). A ustria has reformed lower secondary education (UNESCO ʼs International Standard Classification of Education [ ISCED] Level 2) to reduce the effects of streaming students into different educational tracks too earl y.1 The Austrian government introduced the compulsory of children whose sixth birthday falls before March 1 in the following calendar year may request earlier admission provided that the child is mature enough and has the required social competency to attend school. Six -year-old children considered insufficiently mature to attend school must attend preschool. Primary school comprises primary level I (preschool stage where r equired, and Grades 1 and 2) and primary level II ( Grades 3 and 4). At the lower secondary level (Grades 5 to 8), students ages 10 to 14 can apply for entry to a lower level academic secondary school (Allgemein bildende höhere Schule—Unterstufe) or a compulsory secondary school (Mittelschule). A ustria has reformed lower secondary education (UNESCO ʼs International Standard Classification of Education [ ISCED] Level 2) to reduce the effects of streaming students into different educational tracks too earl y.1 The Austrian government introduced the compulsory of children whose sixth birthday falls before March 1 in the following calendar year may request earlier admission provided that the child is mature enough and has the required social competency to attend school. Six -year-old children considered insufficiently mature to attend school must attend preschool. Primary school comprises primary level I (preschool stage where r equired, and Grades 1 and 2) and primary level II ( Grades 3 and 4). At the lower secondary level (Grades 5 to 8), students ages 10 to 14 can apply for entry to a lower level academic secondary school (Allgemein bildende höhere Schule—Unterstufe) or a compulsory secondary school (Mittelschule). A ustria has reformed lower secondary education (UNESCO ʼs International Standard Classification of Education [ ISCED] Level 2) to reduce the effects of streaming students into different educational tracks too earl y.1 The Austrian government introduced the compulsory of children whose sixth birthday falls before March 1 in the following calendar year may request earlier admission provided that the child is mature enough and has the required social competency to attend school. Six -year-old children considered insufficiently mature to attend school must attend preschool. Primary school comprises primary level I (preschool stage where r equired, and Grades 1 and 2) and primary level II ( Grades 3 and 4). At the lower secondary level (Grades 5 to 8), students ages 10 to 14 can apply for entry to a lower level academic secondary school (Allgemein bildende höhere Schule—Unterstufe) or a compulsory secondary school (Mittelschule). A ustria has reformed lower secondary education (UNESCO ʼs International Standard Classification of Education [ ISCED] Level 2) to reduce the effects of streaming students into different educational tracks too earl y.1 The Austrian government introduced the compulsory of children whose sixth birthday falls before March 1 in the following calendar year may request earlier admission provided that the child is mature enough and has the required social competency to attend school. Six -year-old children considered insufficiently mature to attend school must attend preschool. Primary school comprises primary level I (preschool stage where r equired, and Grades 1 and 2) and primary level II ( Grades 3 and 4). At the lower secondary level (Grades 5 to 8), students ages 10 to 14 can apply for entry to a lower level academic secondary school (Allgemein bildende höhere Schule—Unterstufe) or a compulsory secondary school (Mittelschule). A ustria has reformed lower secondary education (UNESCO ʼs International Standard Classification of Education [ ISCED] Level 2) to reduce the effects of streaming students into different educational tracks too earl y.1 The Austrian government introduced the compulsory of children whose sixth birthday falls before March 1 in the following calendar year may request earlier admission provided that the child is mature enough and has the required social competency to attend school. Six -year-old children considered insufficiently mature to attend school must attend preschool. Primary school comprises primary level I (preschool stage where r equired, and Grades 1 and 2) and primary level II ( Grades 3 and 4). At the lower secondary level (Grades 5 to 8), students ages 10 to 14 can apply for entry to a lower level academic secondary school (Allgemein bildende höhere Schule—Unterstufe) or a compulsory secondary school (Mittelschule). A ustria has reformed lower secondary education (UNESCO ʼs International Standard Classification of Education [ ISCED] Level 2) to reduce the effects of streaming students into different educational tracks too earl y.1 The Austrian government introduced the compulsory of children whose sixth birthday falls before March 1 in the following calendar year may request earlier admission provided that the child is mature enough and has the required social competency to attend school. Six -year-old children considered insufficiently mature to attend school must attend preschool. Primary school comprises primary level I (preschool stage where r equired, and Grades 1 and 2) and primary level II ( Grades 3 and 4). At the lower secondary level (Grades 5 to 8), students ages 10 to 14 can apply for entry to a lower level academic secondary school (Allgemein bildende höhere Schule—Unterstufe) or a compulsory secondary school (Mittelschule). A ustria has reformed lower secondary education (UNESCO ʼs International Standard Classification of Education [ ISCED] Level 2) to reduce the effects of streaming students into different educational tracks too earl y.1 The Austrian government introduced the compulsory | O4: ['of children whose sixth birthday falls before March 1 in the following calendar year may request \nearlier admission provided that the child is mature enough and has the required social competency \nto attend school. Six -year-old children considered insufficiently mature to attend school must \nattend preschool. Primary school comprises primary level I (preschool stage where r equired, and \nGrades 1 and 2) and primary level II ( Grades 3 and 4). At the lower secondary level (Grades 5 to \n8), students ages 10 to 14 can apply for entry to a lower level academic secondary school (Allgemein \nbildende höhere Schule—Unterstufe) or a compulsory secondary school (Mittelschule). \nA\nustria has reformed lower secondary education (UNESCO ʼs International Standard \nClassification of Education [ ISCED] Level 2) to reduce the effects of streaming students into \ndifferent educational tracks too earl y.1 The Austrian government introduced the compulsory\n\nof children whose sixth birthday falls before March 1 in the following calendar year may request \nearlier admission provided that the child is mature enough and has the required social competency \nto attend school. Six -year-old children considered insufficiently mature to attend school must \nattend preschool. Primary school comprises primary level I (preschool stage where r equired, and \nGrades 1 and 2) and primary level II ( Grades 3 and 4). At the lower secondary level (Grades 5 to \n8), students ages 10 to 14 can apply for entry to a lower level academic secondary school (Allgemein \nbildende höhere Schule—Unterstufe) or a compulsory secondary school (Mittelschule). \nA\nustria has reformed lower secondary education (UNESCO ʼs International Standard \nClassification of Education [ ISCED] Level 2) to reduce the effects of streaming students into \ndifferent educational tracks too earl y.1 The Austrian government introduced the compulsory\n\nof children whose sixth birthday falls before March 1 in the following calendar year may request \nearlier admission provided that the child is mature enough and has the required social competency \nto attend school. Six -year-old children considered insufficiently mature to attend school must \nattend preschool. Primary school comprises primary level I (preschool stage where r equired, and \nGrades 1 and 2) and primary level II ( Grades 3 and 4). At the lower secondary level (Grades 5 to \n8), students ages 10 to 14 can apply for entry to a lower level academic secondary school (Allgemein \nbildende höhere Schule—Unterstufe) or a compulsory secondary school (Mittelschule). \nA\nustria has reformed lower secondary education (UNESCO ʼs International Standard \nClassification of Education [ ISCED] Level 2) to reduce the effects of streaming students into \ndifferent educational tracks too earl y.1 The Austrian government introduced the compulsory\n\nof children whose sixth birthday falls before March 1 in the following calendar year may request \nearlier admission provided that the child is mature enough and has the required social competency \nto attend school. Six -year-old children considered insufficiently mature to attend school must \nattend preschool. Primary school comprises primary level I (preschool stage where r equired, and \nGrades 1 and 2) and primary level II ( Grades 3 and 4). At the lower secondary level (Grades 5 to \n8), students ages 10 to 14 can apply for entry to a lower level academic secondary school (Allgemein \nbildende höhere Schule—Unterstufe) or a compulsory secondary school (Mittelschule). \nA\nustria has reformed lower secondary education (UNESCO ʼs International Standard \nClassification of Education [ ISCED] Level 2) to reduce the effects of streaming students into \ndifferent educational tracks too earl y.1 The Austrian government introduced the compulsory\n\nof children whose sixth birthday falls before March 1 in the following calendar year may request \nearlier admission provided that the child is mature enough and has the required social competency \nto attend school. Six -year-old children considered insufficiently mature to attend school must \nattend preschool. Primary school comprises primary level I (preschool stage where r equired, and \nGrades 1 and 2) and primary level II ( Grades 3 and 4). At the lower secondary level (Grades 5 to \n8), students ages 10 to 14 can apply for entry to a lower level academic secondary school (Allgemein \nbildende höhere Schule—Unterstufe) or a compulsory secondary school (Mittelschule). \nA\nustria has reformed lower secondary education (UNESCO ʼs International Standard \nClassification of Education [ ISCED] Level 2) to reduce the effects of streaming students into \ndifferent educational tracks too earl y.1 The Austrian government introduced the compulsory\n\nof children whose sixth birthday falls before March 1 in the following calendar year may request \nearlier admission provided that the child is mature enough and has the required social competency \nto attend school. Six -year-old children considered insufficiently mature to attend school must \nattend preschool. Primary school comprises primary level I (preschool stage where r equired, and \nGrades 1 and 2) and primary level II ( Grades 3 and 4). At the lower secondary level (Grades 5 to \n8), students ages 10 to 14 can apply for entry to a lower level academic secondary school (Allgemein \nbildende höhere Schule—Unterstufe) or a compulsory secondary school (Mittelschule). \nA\nustria has reformed lower secondary education (UNESCO ʼs International Standard \nClassification of Education [ ISCED] Level 2) to reduce the effects of streaming students into \ndifferent educational tracks too earl y.1 The Austrian government introduced the compulsory\n\nof children whose sixth birthday falls before March 1 in the following calendar year may request \nearlier admission provided that the child is mature enough and has the required social competency \nto attend school. Six -year-old children considered insufficiently mature to attend school must \nattend preschool. Primary school comprises primary level I (preschool stage where r equired, and \nGrades 1 and 2) and primary level II ( Grades 3 and 4). At the lower secondary level (Grades 5 to \n8), students ages 10 to 14 can apply for entry to a lower level academic secondary school (Allgemein \nbildende höhere Schule—Unterstufe) or a compulsory secondary school (Mittelschule). \nA\nustria has reformed lower secondary education (UNESCO ʼs International Standard \nClassification of Education [ ISCED] Level 2) to reduce the effects of streaming students into \ndifferent educational tracks too earl y.1 The Austrian government introduced the compulsory\n\nof children whose sixth birthday falls before March 1 in the following calendar year may request \nearlier admission provided that the child is mature enough and has the required social competency \nto attend school. Six -year-old children considered insufficiently mature to attend school must \nattend preschool. Primary school comprises primary level I (preschool stage where r equired, and \nGrades 1 and 2) and primary level II ( Grades 3 and 4). At the lower secondary level (Grades 5 to \n8), students ages 10 to 14 can apply for entry to a lower level academic secondary school (Allgemein \nbildende höhere Schule—Unterstufe) or a compulsory secondary school (Mittelschule). \nA\nustria has reformed lower secondary education (UNESCO ʼs International Standard \nClassification of Education [ ISCED] Level 2) to reduce the effects of streaming students into \ndifferent educational tracks too earl y.1 The Austrian government introduced the compulsory\n\nof children whose sixth birthday falls before March 1 in the following calendar year may request \nearlier admission provided that the child is mature enough and has the required social competency \nto attend school. Six -year-old children considered insufficiently mature to attend school must \nattend preschool. Primary school comprises primary level I (preschool stage where r equired, and \nGrades 1 and 2) and primary level II ( Grades 3 and 4). At the lower secondary level (Grades 5 to \n8), students ages 10 to 14 can apply for entry to a lower level academic secondary school (Allgemein \nbildende höhere Schule—Unterstufe) or a compulsory secondary school (Mittelschule). \nA\nustria has reformed lower secondary education (UNESCO ʼs International Standard \nClassification of Education [ ISCED] Level 2) to reduce the effects of streaming students into \ndifferent educational tracks too earl y.1 The Austrian government introduced the compulsory\n\nof children whose sixth birthday falls before March 1 in the following calendar year may request \nearlier admission provided that the child is mature enough and has the required social competency \nto attend school. Six -year-old children considered insufficiently mature to attend school must \nattend preschool. Primary school comprises primary level I (preschool stage where r equired, and \nGrades 1 and 2) and primary level II ( Grades 3 and 4). At the lower secondary level (Grades 5 to \n8), students ages 10 to 14 can apply for entry to a lower level academic secondary school (Allgemein \nbildende höhere Schule—Unterstufe) or a compulsory secondary school (Mittelschule). \nA\nustria has reformed lower secondary education (UNESCO ʼs International Standard \nClassification of Education [ ISCED] Level 2) to reduce the effects of streaming students into \ndifferent educational tracks too earl y.1 The Austrian government introduced the compulsory\n\nof children whose sixth birthday falls before March 1 in the following calendar year may request \nearlier admission provided that the child is mature enough and has the required social competency \nto attend school. Six -year-old children considered insufficiently mature to attend school must \nattend preschool. Primary school comprises primary level I (preschool stage where r equired, and \nGrades 1 and 2) and primary level II ( Grades 3 and 4). At the lower secondary level (Grades 5 to \n8), students ages 10 to 14 can apply for entry to a lower level academic secondary school (Allgemein \nbildende höhere Schule—Unterstufe) or a compulsory secondary school (Mittelschule). \nA\nustria has reformed lower secondary education (UNESCO ʼs International Standard \nClassification of Education [ ISCED] Level 2) to reduce the effects of streaming students into \ndifferent educational tracks too earl y.1 The Austrian government introduced the compulsory\n\nof children whose sixth birthday falls before March 1 in the following calendar year may request \nearlier admission provided that the child is mature enough and has the required social competency \nto attend school. Six -year-old children considered insufficiently mature to attend school must \nattend preschool. Primary school comprises primary level I (preschool stage where r equired, and \nGrades 1 and 2) and primary level II ( Grades 3 and 4). At the lower secondary level (Grades 5 to \n8), students ages 10 to 14 can apply for entry to a lower level academic secondary school (Allgemein \nbildende höhere Schule—Unterstufe) or a compulsory secondary school (Mittelschule). \nA\nustria has reformed lower secondary education (UNESCO ʼs International Standard \nClassification of Education [ ISCED] Level 2) to reduce the effects of streaming students into \ndifferent educational tracks too earl y.1 The Austrian government introduced the compulsory'] | P4: ['of children whose sixth birthday falls before March 1 in the following calendar year may request \nearlier admission provided that the child is mature enough and has the required social competency \nto attend school. Six -year-old children considered insufficiently mature to attend school must \nattend preschool. Primary school comprises primary level I (preschool stage where r equired, and \nGrades 1 and 2) and primary level II ( Grades 3 and 4). At the lower secondary level (Grades 5 to \n8), students ages 10 to 14 can apply for entry to a lower level academic secondary school (Allgemein \nbildende höhere Schule—Unterstufe) or a compulsory secondary school (Mittelschule). \nA\nustria has reformed lower secondary education (UNESCO ʼs International Standard \nClassification of Education [ ISCED] Level 2) to reduce the effects of streaming students into \ndifferent educational tracks too earl y.1 The Austrian government introduced the compulsory\n\nof children whose sixth birthday falls before March 1 in the following calendar year may request \nearlier admission provided that the child is mature enough and has the required social competency \nto attend school. Six -year-old children considered insufficiently mature to attend school must \nattend preschool. Primary school comprises primary level I (preschool stage where r equired, and \nGrades 1 and 2) and primary level II ( Grades 3 and 4). At the lower secondary level (Grades 5 to \n8), students ages 10 to 14 can apply for entry to a lower level academic secondary school (Allgemein \nbildende höhere Schule—Unterstufe) or a compulsory secondary school (Mittelschule). \nA\nustria has reformed lower secondary education (UNESCO ʼs International Standard \nClassification of Education [ ISCED] Level 2) to reduce the effects of streaming students into \ndifferent educational tracks too earl y.1 The Austrian government introduced the compulsory\n\nof children whose sixth birthday falls before March 1 in the following calendar year may request \nearlier admission provided that the child is mature enough and has the required social competency \nto attend school. Six -year-old children considered insufficiently mature to attend school must \nattend preschool. Primary school comprises primary level I (preschool stage where r equired, and \nGrades 1 and 2) and primary level II ( Grades 3 and 4). At the lower secondary level (Grades 5 to \n8), students ages 10 to 14 can apply for entry to a lower level academic secondary school (Allgemein \nbildende höhere Schule—Unterstufe) or a compulsory secondary school (Mittelschule). \nA\nustria has reformed lower secondary education (UNESCO ʼs International Standard \nClassification of Education [ ISCED] Level 2) to reduce the effects of streaming students into \ndifferent educational tracks too earl y.1 The Austrian government introduced the compulsory\n\nof children whose sixth birthday falls before March 1 in the following calendar year may request \nearlier admission provided that the child is mature enough and has the required social competency \nto attend school. Six -year-old children considered insufficiently mature to attend school must \nattend preschool. Primary school comprises primary level I (preschool stage where r equired, and \nGrades 1 and 2) and primary level II ( Grades 3 and 4). At the lower secondary level (Grades 5 to \n8), students ages 10 to 14 can apply for entry to a lower level academic secondary school (Allgemein \nbildende höhere Schule—Unterstufe) or a compulsory secondary school (Mittelschule). \nA\nustria has reformed lower secondary education (UNESCO ʼs International Standard \nClassification of Education [ ISCED] Level 2) to reduce the effects of streaming students into \ndifferent educational tracks too earl y.1 The Austrian government introduced the compulsory\n\nof children whose sixth birthday falls before March 1 in the following calendar year may request \nearlier admission provided that the child is mature enough and has the required social competency \nto attend school. Six -year-old children considered insufficiently mature to attend school must \nattend preschool. Primary school comprises primary level I (preschool stage where r equired, and \nGrades 1 and 2) and primary level II ( Grades 3 and 4). At the lower secondary level (Grades 5 to \n8), students ages 10 to 14 can apply for entry to a lower level academic secondary school (Allgemein \nbildende höhere Schule—Unterstufe) or a compulsory secondary school (Mittelschule). \nA\nustria has reformed lower secondary education (UNESCO ʼs International Standard \nClassification of Education [ ISCED] Level 2) to reduce the effects of streaming students into \ndifferent educational tracks too earl y.1 The Austrian government introduced the compulsory\n\nof children whose sixth birthday falls before March 1 in the following calendar year may request \nearlier admission provided that the child is mature enough and has the required social competency \nto attend school. Six -year-old children considered insufficiently mature to attend school must \nattend preschool. Primary school comprises primary level I (preschool stage where r equired, and \nGrades 1 and 2) and primary level II ( Grades 3 and 4). At the lower secondary level (Grades 5 to \n8), students ages 10 to 14 can apply for entry to a lower level academic secondary school (Allgemein \nbildende höhere Schule—Unterstufe) or a compulsory secondary school (Mittelschule). \nA\nustria has reformed lower secondary education (UNESCO ʼs International Standard \nClassification of Education [ ISCED] Level 2) to reduce the effects of streaming students into \ndifferent educational tracks too earl y.1 The Austrian government introduced the compulsory\n\nof children whose sixth birthday falls before March 1 in the following calendar year may request \nearlier admission provided that the child is mature enough and has the required social competency \nto attend school. Six -year-old children considered insufficiently mature to attend school must \nattend preschool. Primary school comprises primary level I (preschool stage where r equired, and \nGrades 1 and 2) and primary level II ( Grades 3 and 4). At the lower secondary level (Grades 5 to \n8), students ages 10 to 14 can apply for entry to a lower level academic secondary school (Allgemein \nbildende höhere Schule—Unterstufe) or a compulsory secondary school (Mittelschule). \nA\nustria has reformed lower secondary education (UNESCO ʼs International Standard \nClassification of Education [ ISCED] Level 2) to reduce the effects of streaming students into \ndifferent educational tracks too earl y.1 The Austrian government introduced the compulsory\n\nof children whose sixth birthday falls before March 1 in the following calendar year may request \nearlier admission provided that the child is mature enough and has the required social competency \nto attend school. Six -year-old children considered insufficiently mature to attend school must \nattend preschool. Primary school comprises primary level I (preschool stage where r equired, and \nGrades 1 and 2) and primary level II ( Grades 3 and 4). At the lower secondary level (Grades 5 to \n8), students ages 10 to 14 can apply for entry to a lower level academic secondary school (Allgemein \nbildende höhere Schule—Unterstufe) or a compulsory secondary school (Mittelschule). \nA\nustria has reformed lower secondary education (UNESCO ʼs International Standard \nClassification of Education [ ISCED] Level 2) to reduce the effects of streaming students into \ndifferent educational tracks too earl y.1 The Austrian government introduced the compulsory\n\nof children whose sixth birthday falls before March 1 in the following calendar year may request \nearlier admission provided that the child is mature enough and has the required social competency \nto attend school. Six -year-old children considered insufficiently mature to attend school must \nattend preschool. Primary school comprises primary level I (preschool stage where r equired, and \nGrades 1 and 2) and primary level II ( Grades 3 and 4). At the lower secondary level (Grades 5 to \n8), students ages 10 to 14 can apply for entry to a lower level academic secondary school (Allgemein \nbildende höhere Schule—Unterstufe) or a compulsory secondary school (Mittelschule). \nA\nustria has reformed lower secondary education (UNESCO ʼs International Standard \nClassification of Education [ ISCED] Level 2) to reduce the effects of streaming students into \ndifferent educational tracks too earl y.1 The Austrian government introduced the compulsory\n\nof children whose sixth birthday falls before March 1 in the following calendar year may request \nearlier admission provided that the child is mature enough and has the required social competency \nto attend school. Six -year-old children considered insufficiently mature to attend school must \nattend preschool. Primary school comprises primary level I (preschool stage where r equired, and \nGrades 1 and 2) and primary level II ( Grades 3 and 4). At the lower secondary level (Grades 5 to \n8), students ages 10 to 14 can apply for entry to a lower level academic secondary school (Allgemein \nbildende höhere Schule—Unterstufe) or a compulsory secondary school (Mittelschule). \nA\nustria has reformed lower secondary education (UNESCO ʼs International Standard \nClassification of Education [ ISCED] Level 2) to reduce the effects of streaming students into \ndifferent educational tracks too earl y.1 The Austrian government introduced the compulsory\n\nof children whose sixth birthday falls before March 1 in the following calendar year may request \nearlier admission provided that the child is mature enough and has the required social competency \nto attend school. Six -year-old children considered insufficiently mature to attend school must \nattend preschool. Primary school comprises primary level I (preschool stage where r equired, and \nGrades 1 and 2) and primary level II ( Grades 3 and 4). At the lower secondary level (Grades 5 to \n8), students ages 10 to 14 can apply for entry to a lower level academic secondary school (Allgemein \nbildende höhere Schule—Unterstufe) or a compulsory secondary school (Mittelschule). \nA\nustria has reformed lower secondary education (UNESCO ʼs International Standard \nClassification of Education [ ISCED] Level 2) to reduce the effects of streaming students into \ndifferent educational tracks too earl y.1 The Austrian government introduced the compulsory\n\nof children whose sixth birthday falls before March 1 in the following calendar year may request \nearlier admission provided that the child is mature enough and has the required social competency \nto attend school. Six -year-old children considered insufficiently mature to attend school must \nattend preschool. Primary school comprises primary level I (preschool stage where r equired, and \nGrades 1 and 2) and primary level II ( Grades 3 and 4). At the lower secondary level (Grades 5 to \n8), students ages 10 to 14 can apply for entry to a lower level academic secondary school (Allgemein \nbildende höhere Schule—Unterstufe) or a compulsory secondary school (Mittelschule). \nA\nustria has reformed lower secondary education (UNESCO ʼs International Standard \nClassification of Education [ ISCED] Level 2) to reduce the effects of streaming students into \ndifferent educational tracks too earl y.1 The Austrian government introduced the compulsory'] | Q4: 1 | R4: The score is 1.00 because the single node ranked first contains the exact requirement—"Six-year-old children considered insufficiently mature to attend school must attend preschool"—and confirms that preschool is compulsory before primary school. With no irrelevant nodes present, all relevant information is correctly prioritized. | S4: 0 | T4: The score is 0.00 because sentence 1 of the expected output cannot be supported by any node in the retrieval context; specifically, node 1 states that six‑year‑old children must attend preschool, not a compulsory kindergarten year at age 5. | U4: 1 | V4: The score is 1.00 because the actual output perfectly aligns with the retrieval context—no contradictions were found, indicating complete faithfulness! | W4: 0.3 | X4: The response states that children must complete preschool education before primary school, but it omits the specific details of a compulsory one-year Kindergarten at age 5 that are present in the expected answer. This missing information and lack of exact phrasing reduce alignment. | Y4: 0 | Z4: The score is 0.00 because the only node (rank 1) is irrelevant, as its reason states "The context states that 'Six-year-old children considered insufficiently mature to attend school must attend preschool,' but it does not mention a compulsory year of Kindergarten at age 5, which is the specific requirement in the expected answer." | AA4: 0 | AB4: The score is 0.00 because none of the nodes in the retrieval context provide evidence for the statement about a compulsory year of Kindergarten at age 5. | AC4: 1 | AD4: The score is 1.00 because there are no contradictions, indicating the actual output perfectly aligns with the retrieval context! | AE4: 0 | AF4: The actual answer states that six‑year‑old children who are deemed insufficiently mature must attend preschool, whereas the expected answer specifies that Austrian children must complete a compulsory year of kindergarten at age five before starting primary school. The factual claims differ, key details such as age five and compulsory kindergarten are missing, and the statements are not semantically equivalent. | AG4: 1 | AH4: The score is 1.00 because the single node ranked first contains the exact requirement—"Six-year-old children considered insufficiently mature to attend school must attend preschool"—and confirms that preschool is compulsory before primary school. With no irrelevant nodes present, all relevant information is correctly prioritized. | AI4: 0 | AJ4: The score is 0.00 because sentence 1 of the expected output cannot be supported by any node in the retrieval context; specifically, node 1 states that six‑year‑old children must attend preschool, not a compulsory kindergarten year at age 5. | AK4: 1 | AL4: The score is 1.00 because the actual output perfectly aligns with the retrieval context—no contradictions were found, indicating complete faithfulness! | AM4: 0 | AN4: The actual output states that six‑year‑old children deemed insufficiently mature must attend preschool, which does not match the expected claim that Austrian children must complete a compulsory year of Kindergarten at age 5 before primary school. The key details—age 5, compulsory Kindergarten year, and Austrian context—are missing, and the factual claim differs, leading to a low score. | AO4: 0 | AP4: The score is 0.00 because the only node (rank 1) is irrelevant; it only says "The context mentions that "Six-year-old children considered insufficiently mature to attend school must attend preschool," but it does not state that Austrian children must complete one compulsory year of Kindergarten at age 5 before beginning primary school. Therefore, it does not provide the specific requirement required for the expected answer." | AQ4: 0 | AR4: The score is 0.00 because the expected sentence cannot be supported by the retrieval context; node 1 mentions preschool for six‑year‑olds but does not state a compulsory year of Kindergarten at age 5. | AS4: 0.5 | AT4: The score is 0.50 because the actual output incorrectly states that there is no specific age or year requirement for mandatory early education, while the context clearly specifies that children whose sixth birthday falls before March 1 of the following calendar year may request earlier admission, and that maturity and social competence are also required. This partial mismatch justifies a moderate faithfulness score. | AU4: 0 | AV4: The actual output contradicts the expected claim by stating there is no compulsory kindergarten year at age 5, whereas the expected output explicitly requires one year of kindergarten at that age. This direct contradiction and omission of the key point result in a low score. | AW4: 1 | AX4: The score is 1.00 because the only node in the retrieval contexts is ranked first and is relevant, as it states "Six -year-old children considered insufficiently mature to attend school must attend preschool" and "Primary school comprises primary level I (preschool stage where required, and Grades 1 and 2)". With no irrelevant nodes to outrank it, the contextual precision remains at its maximum. | AY4: 0 | AZ4: The score is 0.00 because none of the nodes in the retrieval context provide evidence for the statement about a compulsory year of Kindergarten at age 5; the only related mention is node 1, which refers to six‑year‑old children attending preschool, not a compulsory year at age 5. | BA4: 0.75 | BB4: The score is 0.75 because the actual output incorrectly states that all children must attend preschool before primary school, which contradicts the context that only six‑year‑olds who are insufficiently mature are required to attend preschool. | BC4: 0 | BD4: The actual output contradicts the expected statement by describing a mandatory early education program for six‑year‑olds with no defined duration, whereas the expected output specifies a single compulsory year of Kindergarten at age five. Key details such as the age requirement and the one‑year duration are missing, leading to a mismatch. | BE4: 1 | BF4: The score is 1.00 because the only node in the retrieval contexts is ranked first and is relevant, as it states "Six -year-old children considered insufficiently mature to attend school must attend preschool" and "Primary school comprises primary level I (preschool stage where required, and Grades 1 and 2)". With no irrelevant nodes to outrank it, the contextual precision remains at its maximum. | BG4: 0 | BH4: The score is 0.00 because none of the nodes in the retrieval context provide evidence for the statement about a compulsory year of Kindergarten at age 5; the only related mention is node 1, which refers to six‑year‑old children attending preschool, not a compulsory year at age 5. | BI4: 0.66666667 | BJ4: The score is 0.67 because the actual output incorrectly states that compulsory schooling starts before primary school, whereas the context says preschool is part of primary school and compulsory schooling begins there. | BK4: 0 | BL4: The actual output contradicts the expected statement by claiming compulsory schooling starts at age seven and omits the mandatory kindergarten year at age five. It also fails to mention the key point that Austrian children must complete a compulsory year of kindergarten before primary school. This mismatch results in a low score. | BM4: synthetic
A5: 6 | B5: At what age does compulsory primary education begin in Azerbaijan, and how long does the compulsory education period last? | C5: Compulsory primary education begins at age 6, and the total compulsory education period lasts nine years. | D5: Primary: Compulsory level of education that begins at age 6 and covers the first 4 years (Grades 1–4). | E5: To answer this question, I will walk you through my thought process step by step. Step 1: Identify relevant information from the context. From the provided text, I found the following information: * There are two types of schools in Azerbaijan: public and private. * Exhibit 1 provides levels of education in Azerbaijani schools. * Preprimary education encompasses children from birth to age 6 and is not compulsory. * Primary education is a compulsory level that begins at age 6. Step 2: Determine the relevant information for the question. To answer the question, I need to find the information about when compulsory primary education begins and how long it lasts. From the text, I found: * Compulsory primary education begins at age 6 (mentioned in the Primary level of education description). * The primary level covers the first 4 years (Grades 1–4). Step 3: Combine the relevant information. Based on the context, I can conclude that compulsory primary education begins at age 6 and lasts for 4 years. Answer: Compulsory primary education in Azerbaijan begins at age 6 and lasts for 4 years. | F5: Okay, let's analyze the context to answer your question. 1. **Identify the relevant information:** The context describes the "Primary" level of education in Azerbaijan. 2. **Extract the details:** It states that primary education "begins at age 6 and covers the first 4 years (Grades 1–4)." Therefore, compulsory primary education begins at age 6 and lasts for 4 years. | G5: Compulsory primary education in Azerbaijan begins at the age of **6 years old** and lasts for **4 years** (Grades 1–4). | H5: ['AZERBAIJAN \nPIRLS 2021 ENCYCLOPEDIA 2 \nThere are two types of schools in Azerbaijan , classified based on their ownership: public \nschools, which belong to the state and do not directly seek outside funding, and private schools , \nwhich are funded directly through education fees. \nExhibit 1: Levels of Education in Azerbaijani Schools \nLevel of Education Description2 \nPreprimary Encompasses children from birth to age 6 and is not compulsory. It is provided \nin nurseries (children under age 3), Kindergartens (children ages 3–5 or 6), and \nschools (children ages 5–6). \nPrimary Compulsory level of education that begins at age 6 and covers the first 4 years \n(Grades 1–4). \nGeneral \nSecondary \nLower Secondary Also compulsory and covers groups of students ages 10–15 (Grades 5–9). At \nthe end of Grade 9, students take final assessments to receive a document that \nis considered a basis for continuing to the next level of education. After', 'AZERBAIJAN \nPIRLS 2021 ENCYCLOPEDIA 2 \nThere are two types of schools in Azerbaijan , classified based on their ownership: public \nschools, which belong to the state and do not directly seek outside funding, and private schools , \nwhich are funded directly through education fees. \nExhibit 1: Levels of Education in Azerbaijani Schools \nLevel of Education Description2 \nPreprimary Encompasses children from birth to age 6 and is not compulsory. It is provided \nin nurseries (children under age 3), Kindergartens (children ages 3–5 or 6), and \nschools (children ages 5–6). \nPrimary Compulsory level of education that begins at age 6 and covers the first 4 years \n(Grades 1–4). \nGeneral \nSecondary \nLower Secondary Also compulsory and covers groups of students ages 10–15 (Grades 5–9). At \nthe end of Grade 9, students take final assessments to receive a document that \nis considered a basis for continuing to the next level of education. After', 'AZERBAIJAN \nPIRLS 2021 ENCYCLOPEDIA 2 \nThere are two types of schools in Azerbaijan , classified based on their ownership: public \nschools, which belong to the state and do not directly seek outside funding, and private schools , \nwhich are funded directly through education fees. \nExhibit 1: Levels of Education in Azerbaijani Schools \nLevel of Education Description2 \nPreprimary Encompasses children from birth to age 6 and is not compulsory. It is provided \nin nurseries (children under age 3), Kindergartens (children ages 3–5 or 6), and \nschools (children ages 5–6). \nPrimary Compulsory level of education that begins at age 6 and covers the first 4 years \n(Grades 1–4). \nGeneral \nSecondary \nLower Secondary Also compulsory and covers groups of students ages 10–15 (Grades 5–9). At \nthe end of Grade 9, students take final assessments to receive a document that \nis considered a basis for continuing to the next level of education. After', 'AZERBAIJAN \nPIRLS 2021 ENCYCLOPEDIA 2 \nThere are two types of schools in Azerbaijan , classified based on their ownership: public \nschools, which belong to the state and do not directly seek outside funding, and private schools , \nwhich are funded directly through education fees. \nExhibit 1: Levels of Education in Azerbaijani Schools \nLevel of Education Description2 \nPreprimary Encompasses children from birth to age 6 and is not compulsory. It is provided \nin nurseries (children under age 3), Kindergartens (children ages 3–5 or 6), and \nschools (children ages 5–6). \nPrimary Compulsory level of education that begins at age 6 and covers the first 4 years \n(Grades 1–4). \nGeneral \nSecondary \nLower Secondary Also compulsory and covers groups of students ages 10–15 (Grades 5–9). At \nthe end of Grade 9, students take final assessments to receive a document that \nis considered a basis for continuing to the next level of education. After'] | I5: ['AZERBAIJAN \nPIRLS 2021 ENCYCLOPEDIA 2 \nThere are two types of schools in Azerbaijan , classified based on their ownership: public \nschools, which belong to the state and do not directly seek outside funding, and private schools , \nwhich are funded directly through education fees. \nExhibit 1: Levels of Education in Azerbaijani Schools \nLevel of Education Description2 \nPreprimary Encompasses children from birth to age 6 and is not compulsory. It is provided \nin nurseries (children under age 3), Kindergartens (children ages 3–5 or 6), and \nschools (children ages 5–6). \nPrimary Compulsory level of education that begins at age 6 and covers the first 4 years \n(Grades 1–4). \nGeneral \nSecondary \nLower Secondary Also compulsory and covers groups of students ages 10–15 (Grades 5–9). At \nthe end of Grade 9, students take final assessments to receive a document that \nis considered a basis for continuing to the next level of education. After', 'AZERBAIJAN \nPIRLS 2021 ENCYCLOPEDIA 2 \nThere are two types of schools in Azerbaijan , classified based on their ownership: public \nschools, which belong to the state and do not directly seek outside funding, and private schools , \nwhich are funded directly through education fees. \nExhibit 1: Levels of Education in Azerbaijani Schools \nLevel of Education Description2 \nPreprimary Encompasses children from birth to age 6 and is not compulsory. It is provided \nin nurseries (children under age 3), Kindergartens (children ages 3–5 or 6), and \nschools (children ages 5–6). \nPrimary Compulsory level of education that begins at age 6 and covers the first 4 years \n(Grades 1–4). \nGeneral \nSecondary \nLower Secondary Also compulsory and covers groups of students ages 10–15 (Grades 5–9). At \nthe end of Grade 9, students take final assessments to receive a document that \nis considered a basis for continuing to the next level of education. After', 'AZERBAIJAN \nPIRLS 2021 ENCYCLOPEDIA 2 \nThere are two types of schools in Azerbaijan , classified based on their ownership: public \nschools, which belong to the state and do not directly seek outside funding, and private schools , \nwhich are funded directly through education fees. \nExhibit 1: Levels of Education in Azerbaijani Schools \nLevel of Education Description2 \nPreprimary Encompasses children from birth to age 6 and is not compulsory. It is provided \nin nurseries (children under age 3), Kindergartens (children ages 3–5 or 6), and \nschools (children ages 5–6). \nPrimary Compulsory level of education that begins at age 6 and covers the first 4 years \n(Grades 1–4). \nGeneral \nSecondary \nLower Secondary Also compulsory and covers groups of students ages 10–15 (Grades 5–9). At \nthe end of Grade 9, students take final assessments to receive a document that \nis considered a basis for continuing to the next level of education. After', 'AZERBAIJAN \nPIRLS 2021 ENCYCLOPEDIA 2 \nThere are two types of schools in Azerbaijan , classified based on their ownership: public \nschools, which belong to the state and do not directly seek outside funding, and private schools , \nwhich are funded directly through education fees. \nExhibit 1: Levels of Education in Azerbaijani Schools \nLevel of Education Description2 \nPreprimary Encompasses children from birth to age 6 and is not compulsory. It is provided \nin nurseries (children under age 3), Kindergartens (children ages 3–5 or 6), and \nschools (children ages 5–6). \nPrimary Compulsory level of education that begins at age 6 and covers the first 4 years \n(Grades 1–4). \nGeneral \nSecondary \nLower Secondary Also compulsory and covers groups of students ages 10–15 (Grades 5–9). At \nthe end of Grade 9, students take final assessments to receive a document that \nis considered a basis for continuing to the next level of education. After'] | J5: ['AZERBAIJAN \nPIRLS 2021 ENCYCLOPEDIA 2 \nThere are two types of schools in Azerbaijan , classified based on their ownership: public \nschools, which belong to the state and do not directly seek outside funding, and private schools , \nwhich are funded directly through education fees. \nExhibit 1: Levels of Education in Azerbaijani Schools \nLevel of Education Description2 \nPreprimary Encompasses children from birth to age 6 and is not compulsory. It is provided \nin nurseries (children under age 3), Kindergartens (children ages 3–5 or 6), and \nschools (children ages 5–6). \nPrimary Compulsory level of education that begins at age 6 and covers the first 4 years \n(Grades 1–4). \nGeneral \nSecondary \nLower Secondary Also compulsory and covers groups of students ages 10–15 (Grades 5–9). At \nthe end of Grade 9, students take final assessments to receive a document that \nis considered a basis for continuing to the next level of education. After', 'AZERBAIJAN \nPIRLS 2021 ENCYCLOPEDIA 2 \nThere are two types of schools in Azerbaijan , classified based on their ownership: public \nschools, which belong to the state and do not directly seek outside funding, and private schools , \nwhich are funded directly through education fees. \nExhibit 1: Levels of Education in Azerbaijani Schools \nLevel of Education Description2 \nPreprimary Encompasses children from birth to age 6 and is not compulsory. It is provided \nin nurseries (children under age 3), Kindergartens (children ages 3–5 or 6), and \nschools (children ages 5–6). \nPrimary Compulsory level of education that begins at age 6 and covers the first 4 years \n(Grades 1–4). \nGeneral \nSecondary \nLower Secondary Also compulsory and covers groups of students ages 10–15 (Grades 5–9). At \nthe end of Grade 9, students take final assessments to receive a document that \nis considered a basis for continuing to the next level of education. After', 'AZERBAIJAN \nPIRLS 2021 ENCYCLOPEDIA 2 \nThere are two types of schools in Azerbaijan , classified based on their ownership: public \nschools, which belong to the state and do not directly seek outside funding, and private schools , \nwhich are funded directly through education fees. \nExhibit 1: Levels of Education in Azerbaijani Schools \nLevel of Education Description2 \nPreprimary Encompasses children from birth to age 6 and is not compulsory. It is provided \nin nurseries (children under age 3), Kindergartens (children ages 3–5 or 6), and \nschools (children ages 5–6). \nPrimary Compulsory level of education that begins at age 6 and covers the first 4 years \n(Grades 1–4). \nGeneral \nSecondary \nLower Secondary Also compulsory and covers groups of students ages 10–15 (Grades 5–9). At \nthe end of Grade 9, students take final assessments to receive a document that \nis considered a basis for continuing to the next level of education. After', 'AZERBAIJAN \nPIRLS 2021 ENCYCLOPEDIA 2 \nThere are two types of schools in Azerbaijan , classified based on their ownership: public \nschools, which belong to the state and do not directly seek outside funding, and private schools , \nwhich are funded directly through education fees. \nExhibit 1: Levels of Education in Azerbaijani Schools \nLevel of Education Description2 \nPreprimary Encompasses children from birth to age 6 and is not compulsory. It is provided \nin nurseries (children under age 3), Kindergartens (children ages 3–5 or 6), and \nschools (children ages 5–6). \nPrimary Compulsory level of education that begins at age 6 and covers the first 4 years \n(Grades 1–4). \nGeneral \nSecondary \nLower Secondary Also compulsory and covers groups of students ages 10–15 (Grades 5–9). At \nthe end of Grade 9, students take final assessments to receive a document that \nis considered a basis for continuing to the next level of education. After'] | K5: According to Exhibit 1: Levels of Education in Azerbaijani Schools, compulsory primary education begins at age 6 and continues through Lower Secondary (Grades 5-9) until age 15. This means that the total length of the compulsory education period is from age 6 to 15, lasting a total of 9 years. Therefore, the final answer to the main question is: "Compulsory primary education begins at age 6 and lasts for 9 years, from age 6 to 15." | L5: Compulsory primary education in Azerbaijan begins at age 6. The compulsory education period lasts for the first four years, covering Grades 1 through 4. This equates to a total of ten years of schooling, as students typically progress from age 6 to 10 for this initial compulsory phase. Therefore, the compulsory education period spans from age 6 to 10. | M5: Compulsory primary education in Azerbaijan begins at age 6. The entire compulsory education period lasts 9 years, encompassing 4 years of primary school (Grades 1-4) and 5 years of lower secondary school (Grades 5-9). | N5: AZERBAIJAN PIRLS 2021 ENCYCLOPEDIA 2 There are two types of schools in Azerbaijan , classified based on their ownership: public schools, which belong to the state and do not directly seek outside funding, and private schools , which are funded directly through education fees. Exhibit 1: Levels of Education in Azerbaijani Schools Level of Education Description2 Preprimary Encompasses children from birth to age 6 and is not compulsory. It is provided in nurseries (children under age 3), Kindergartens (children ages 3–5 or 6), and schools (children ages 5–6). Primary Compulsory level of education that begins at age 6 and covers the first 4 years (Grades 1–4). General Secondary Lower Secondary Also compulsory and covers groups of students ages 10–15 (Grades 5–9). At the end of Grade 9, students take final assessments to receive a document that is considered a basis for continuing to the next level of education. After AZERBAIJAN PIRLS 2021 ENCYCLOPEDIA 2 There are two types of schools in Azerbaijan , classified based on their ownership: public schools, which belong to the state and do not directly seek outside funding, and private schools , which are funded directly through education fees. Exhibit 1: Levels of Education in Azerbaijani Schools Level of Education Description2 Preprimary Encompasses children from birth to age 6 and is not compulsory. It is provided in nurseries (children under age 3), Kindergartens (children ages 3–5 or 6), and schools (children ages 5–6). Primary Compulsory level of education that begins at age 6 and covers the first 4 years (Grades 1–4). General Secondary Lower Secondary Also compulsory and covers groups of students ages 10–15 (Grades 5–9). At the end of Grade 9, students take final assessments to receive a document that is considered a basis for continuing to the next level of education. After AZERBAIJAN PIRLS 2021 ENCYCLOPEDIA 2 There are two types of schools in Azerbaijan , classified based on their ownership: public schools, which belong to the state and do not directly seek outside funding, and private schools , which are funded directly through education fees. Exhibit 1: Levels of Education in Azerbaijani Schools Level of Education Description2 Preprimary Encompasses children from birth to age 6 and is not compulsory. It is provided in nurseries (children under age 3), Kindergartens (children ages 3–5 or 6), and schools (children ages 5–6). Primary Compulsory level of education that begins at age 6 and covers the first 4 years (Grades 1–4). General Secondary Lower Secondary Also compulsory and covers groups of students ages 10–15 (Grades 5–9). At the end of Grade 9, students take final assessments to receive a document that is considered a basis for continuing to the next level of education. After AZERBAIJAN PIRLS 2021 ENCYCLOPEDIA 2 There are two types of schools in Azerbaijan , classified based on their ownership: public schools, which belong to the state and do not directly seek outside funding, and private schools , which are funded directly through education fees. Exhibit 1: Levels of Education in Azerbaijani Schools Level of Education Description2 Preprimary Encompasses children from birth to age 6 and is not compulsory. It is provided in nurseries (children under age 3), Kindergartens (children ages 3–5 or 6), and schools (children ages 5–6). Primary Compulsory level of education that begins at age 6 and covers the first 4 years (Grades 1–4). General Secondary Lower Secondary Also compulsory and covers groups of students ages 10–15 (Grades 5–9). At the end of Grade 9, students take final assessments to receive a document that is considered a basis for continuing to the next level of education. After AZERBAIJAN PIRLS 2021 ENCYCLOPEDIA 2 There are two types of schools in Azerbaijan , classified based on their ownership: public schools, which belong to the state and do not directly seek outside funding, and private schools , which are funded directly through education fees. Exhibit 1: Levels of Education in Azerbaijani Schools Level of Education Description2 Preprimary Encompasses children from birth to age 6 and is not compulsory. It is provided in nurseries (children under age 3), Kindergartens (children ages 3–5 or 6), and schools (children ages 5–6). Primary Compulsory level of education that begins at age 6 and covers the first 4 years (Grades 1–4). General Secondary Lower Secondary Also compulsory and covers groups of students ages 10–15 (Grades 5–9). At the end of Grade 9, students take final assessments to receive a document that is considered a basis for continuing to the next level of education. After AZERBAIJAN PIRLS 2021 ENCYCLOPEDIA 2 There are two types of schools in Azerbaijan , classified based on their ownership: public schools, which belong to the state and do not directly seek outside funding, and private schools , which are funded directly through education fees. Exhibit 1: Levels of Education in Azerbaijani Schools Level of Education Description2 Preprimary Encompasses children from birth to age 6 and is not compulsory. It is provided in nurseries (children under age 3), Kindergartens (children ages 3–5 or 6), and schools (children ages 5–6). Primary Compulsory level of education that begins at age 6 and covers the first 4 years (Grades 1–4). General Secondary Lower Secondary Also compulsory and covers groups of students ages 10–15 (Grades 5–9). At the end of Grade 9, students take final assessments to receive a document that is considered a basis for continuing to the next level of education. After AZERBAIJAN PIRLS 2021 ENCYCLOPEDIA 2 There are two types of schools in Azerbaijan , classified based on their ownership: public schools, which belong to the state and do not directly seek outside funding, and private schools , which are funded directly through education fees. Exhibit 1: Levels of Education in Azerbaijani Schools Level of Education Description2 Preprimary Encompasses children from birth to age 6 and is not compulsory. It is provided in nurseries (children under age 3), Kindergartens (children ages 3–5 or 6), and schools (children ages 5–6). Primary Compulsory level of education that begins at age 6 and covers the first 4 years (Grades 1–4). General Secondary Lower Secondary Also compulsory and covers groups of students ages 10–15 (Grades 5–9). At the end of Grade 9, students take final assessments to receive a document that is considered a basis for continuing to the next level of education. After AZERBAIJAN PIRLS 2021 ENCYCLOPEDIA 2 There are two types of schools in Azerbaijan , classified based on their ownership: public schools, which belong to the state and do not directly seek outside funding, and private schools , which are funded directly through education fees. Exhibit 1: Levels of Education in Azerbaijani Schools Level of Education Description2 Preprimary Encompasses children from birth to age 6 and is not compulsory. It is provided in nurseries (children under age 3), Kindergartens (children ages 3–5 or 6), and schools (children ages 5–6). Primary Compulsory level of education that begins at age 6 and covers the first 4 years (Grades 1–4). General Secondary Lower Secondary Also compulsory and covers groups of students ages 10–15 (Grades 5–9). At the end of Grade 9, students take final assessments to receive a document that is considered a basis for continuing to the next level of education. After | O5: ['AZERBAIJAN \nPIRLS 2021 ENCYCLOPEDIA 2 \nThere are two types of schools in Azerbaijan , classified based on their ownership: public \nschools, which belong to the state and do not directly seek outside funding, and private schools , \nwhich are funded directly through education fees. \nExhibit 1: Levels of Education in Azerbaijani Schools \nLevel of Education Description2 \nPreprimary Encompasses children from birth to age 6 and is not compulsory. It is provided \nin nurseries (children under age 3), Kindergartens (children ages 3–5 or 6), and \nschools (children ages 5–6). \nPrimary Compulsory level of education that begins at age 6 and covers the first 4 years \n(Grades 1–4). \nGeneral \nSecondary \nLower Secondary Also compulsory and covers groups of students ages 10–15 (Grades 5–9). At \nthe end of Grade 9, students take final assessments to receive a document that \nis considered a basis for continuing to the next level of education. After\n\nAZERBAIJAN \nPIRLS 2021 ENCYCLOPEDIA 2 \nThere are two types of schools in Azerbaijan , classified based on their ownership: public \nschools, which belong to the state and do not directly seek outside funding, and private schools , \nwhich are funded directly through education fees. \nExhibit 1: Levels of Education in Azerbaijani Schools \nLevel of Education Description2 \nPreprimary Encompasses children from birth to age 6 and is not compulsory. It is provided \nin nurseries (children under age 3), Kindergartens (children ages 3–5 or 6), and \nschools (children ages 5–6). \nPrimary Compulsory level of education that begins at age 6 and covers the first 4 years \n(Grades 1–4). \nGeneral \nSecondary \nLower Secondary Also compulsory and covers groups of students ages 10–15 (Grades 5–9). At \nthe end of Grade 9, students take final assessments to receive a document that \nis considered a basis for continuing to the next level of education. After\n\nAZERBAIJAN \nPIRLS 2021 ENCYCLOPEDIA 2 \nThere are two types of schools in Azerbaijan , classified based on their ownership: public \nschools, which belong to the state and do not directly seek outside funding, and private schools , \nwhich are funded directly through education fees. \nExhibit 1: Levels of Education in Azerbaijani Schools \nLevel of Education Description2 \nPreprimary Encompasses children from birth to age 6 and is not compulsory. It is provided \nin nurseries (children under age 3), Kindergartens (children ages 3–5 or 6), and \nschools (children ages 5–6). \nPrimary Compulsory level of education that begins at age 6 and covers the first 4 years \n(Grades 1–4). \nGeneral \nSecondary \nLower Secondary Also compulsory and covers groups of students ages 10–15 (Grades 5–9). At \nthe end of Grade 9, students take final assessments to receive a document that \nis considered a basis for continuing to the next level of education. After\n\nAZERBAIJAN \nPIRLS 2021 ENCYCLOPEDIA 2 \nThere are two types of schools in Azerbaijan , classified based on their ownership: public \nschools, which belong to the state and do not directly seek outside funding, and private schools , \nwhich are funded directly through education fees. \nExhibit 1: Levels of Education in Azerbaijani Schools \nLevel of Education Description2 \nPreprimary Encompasses children from birth to age 6 and is not compulsory. It is provided \nin nurseries (children under age 3), Kindergartens (children ages 3–5 or 6), and \nschools (children ages 5–6). \nPrimary Compulsory level of education that begins at age 6 and covers the first 4 years \n(Grades 1–4). \nGeneral \nSecondary \nLower Secondary Also compulsory and covers groups of students ages 10–15 (Grades 5–9). At \nthe end of Grade 9, students take final assessments to receive a document that \nis considered a basis for continuing to the next level of education. After\n\nAZERBAIJAN \nPIRLS 2021 ENCYCLOPEDIA 2 \nThere are two types of schools in Azerbaijan , classified based on their ownership: public \nschools, which belong to the state and do not directly seek outside funding, and private schools , \nwhich are funded directly through education fees. \nExhibit 1: Levels of Education in Azerbaijani Schools \nLevel of Education Description2 \nPreprimary Encompasses children from birth to age 6 and is not compulsory. It is provided \nin nurseries (children under age 3), Kindergartens (children ages 3–5 or 6), and \nschools (children ages 5–6). \nPrimary Compulsory level of education that begins at age 6 and covers the first 4 years \n(Grades 1–4). \nGeneral \nSecondary \nLower Secondary Also compulsory and covers groups of students ages 10–15 (Grades 5–9). At \nthe end of Grade 9, students take final assessments to receive a document that \nis considered a basis for continuing to the next level of education. After\n\nAZERBAIJAN \nPIRLS 2021 ENCYCLOPEDIA 2 \nThere are two types of schools in Azerbaijan , classified based on their ownership: public \nschools, which belong to the state and do not directly seek outside funding, and private schools , \nwhich are funded directly through education fees. \nExhibit 1: Levels of Education in Azerbaijani Schools \nLevel of Education Description2 \nPreprimary Encompasses children from birth to age 6 and is not compulsory. It is provided \nin nurseries (children under age 3), Kindergartens (children ages 3–5 or 6), and \nschools (children ages 5–6). \nPrimary Compulsory level of education that begins at age 6 and covers the first 4 years \n(Grades 1–4). \nGeneral \nSecondary \nLower Secondary Also compulsory and covers groups of students ages 10–15 (Grades 5–9). At \nthe end of Grade 9, students take final assessments to receive a document that \nis considered a basis for continuing to the next level of education. After\n\nAZERBAIJAN \nPIRLS 2021 ENCYCLOPEDIA 2 \nThere are two types of schools in Azerbaijan , classified based on their ownership: public \nschools, which belong to the state and do not directly seek outside funding, and private schools , \nwhich are funded directly through education fees. \nExhibit 1: Levels of Education in Azerbaijani Schools \nLevel of Education Description2 \nPreprimary Encompasses children from birth to age 6 and is not compulsory. It is provided \nin nurseries (children under age 3), Kindergartens (children ages 3–5 or 6), and \nschools (children ages 5–6). \nPrimary Compulsory level of education that begins at age 6 and covers the first 4 years \n(Grades 1–4). \nGeneral \nSecondary \nLower Secondary Also compulsory and covers groups of students ages 10–15 (Grades 5–9). At \nthe end of Grade 9, students take final assessments to receive a document that \nis considered a basis for continuing to the next level of education. After\n\nAZERBAIJAN \nPIRLS 2021 ENCYCLOPEDIA 2 \nThere are two types of schools in Azerbaijan , classified based on their ownership: public \nschools, which belong to the state and do not directly seek outside funding, and private schools , \nwhich are funded directly through education fees. \nExhibit 1: Levels of Education in Azerbaijani Schools \nLevel of Education Description2 \nPreprimary Encompasses children from birth to age 6 and is not compulsory. It is provided \nin nurseries (children under age 3), Kindergartens (children ages 3–5 or 6), and \nschools (children ages 5–6). \nPrimary Compulsory level of education that begins at age 6 and covers the first 4 years \n(Grades 1–4). \nGeneral \nSecondary \nLower Secondary Also compulsory and covers groups of students ages 10–15 (Grades 5–9). At \nthe end of Grade 9, students take final assessments to receive a document that \nis considered a basis for continuing to the next level of education. After'] | P5: ['AZERBAIJAN \nPIRLS 2021 ENCYCLOPEDIA 2 \nThere are two types of schools in Azerbaijan , classified based on their ownership: public \nschools, which belong to the state and do not directly seek outside funding, and private schools , \nwhich are funded directly through education fees. \nExhibit 1: Levels of Education in Azerbaijani Schools \nLevel of Education Description2 \nPreprimary Encompasses children from birth to age 6 and is not compulsory. It is provided \nin nurseries (children under age 3), Kindergartens (children ages 3–5 or 6), and \nschools (children ages 5–6). \nPrimary Compulsory level of education that begins at age 6 and covers the first 4 years \n(Grades 1–4). \nGeneral \nSecondary \nLower Secondary Also compulsory and covers groups of students ages 10–15 (Grades 5–9). At \nthe end of Grade 9, students take final assessments to receive a document that \nis considered a basis for continuing to the next level of education. After\n\nAZERBAIJAN \nPIRLS 2021 ENCYCLOPEDIA 2 \nThere are two types of schools in Azerbaijan , classified based on their ownership: public \nschools, which belong to the state and do not directly seek outside funding, and private schools , \nwhich are funded directly through education fees. \nExhibit 1: Levels of Education in Azerbaijani Schools \nLevel of Education Description2 \nPreprimary Encompasses children from birth to age 6 and is not compulsory. It is provided \nin nurseries (children under age 3), Kindergartens (children ages 3–5 or 6), and \nschools (children ages 5–6). \nPrimary Compulsory level of education that begins at age 6 and covers the first 4 years \n(Grades 1–4). \nGeneral \nSecondary \nLower Secondary Also compulsory and covers groups of students ages 10–15 (Grades 5–9). At \nthe end of Grade 9, students take final assessments to receive a document that \nis considered a basis for continuing to the next level of education. After\n\nAZERBAIJAN \nPIRLS 2021 ENCYCLOPEDIA 2 \nThere are two types of schools in Azerbaijan , classified based on their ownership: public \nschools, which belong to the state and do not directly seek outside funding, and private schools , \nwhich are funded directly through education fees. \nExhibit 1: Levels of Education in Azerbaijani Schools \nLevel of Education Description2 \nPreprimary Encompasses children from birth to age 6 and is not compulsory. It is provided \nin nurseries (children under age 3), Kindergartens (children ages 3–5 or 6), and \nschools (children ages 5–6). \nPrimary Compulsory level of education that begins at age 6 and covers the first 4 years \n(Grades 1–4). \nGeneral \nSecondary \nLower Secondary Also compulsory and covers groups of students ages 10–15 (Grades 5–9). At \nthe end of Grade 9, students take final assessments to receive a document that \nis considered a basis for continuing to the next level of education. After\n\nAZERBAIJAN \nPIRLS 2021 ENCYCLOPEDIA 2 \nThere are two types of schools in Azerbaijan , classified based on their ownership: public \nschools, which belong to the state and do not directly seek outside funding, and private schools , \nwhich are funded directly through education fees. \nExhibit 1: Levels of Education in Azerbaijani Schools \nLevel of Education Description2 \nPreprimary Encompasses children from birth to age 6 and is not compulsory. It is provided \nin nurseries (children under age 3), Kindergartens (children ages 3–5 or 6), and \nschools (children ages 5–6). \nPrimary Compulsory level of education that begins at age 6 and covers the first 4 years \n(Grades 1–4). \nGeneral \nSecondary \nLower Secondary Also compulsory and covers groups of students ages 10–15 (Grades 5–9). At \nthe end of Grade 9, students take final assessments to receive a document that \nis considered a basis for continuing to the next level of education. After\n\nAZERBAIJAN \nPIRLS 2021 ENCYCLOPEDIA 2 \nThere are two types of schools in Azerbaijan , classified based on their ownership: public \nschools, which belong to the state and do not directly seek outside funding, and private schools , \nwhich are funded directly through education fees. \nExhibit 1: Levels of Education in Azerbaijani Schools \nLevel of Education Description2 \nPreprimary Encompasses children from birth to age 6 and is not compulsory. It is provided \nin nurseries (children under age 3), Kindergartens (children ages 3–5 or 6), and \nschools (children ages 5–6). \nPrimary Compulsory level of education that begins at age 6 and covers the first 4 years \n(Grades 1–4). \nGeneral \nSecondary \nLower Secondary Also compulsory and covers groups of students ages 10–15 (Grades 5–9). At \nthe end of Grade 9, students take final assessments to receive a document that \nis considered a basis for continuing to the next level of education. After\n\nAZERBAIJAN \nPIRLS 2021 ENCYCLOPEDIA 2 \nThere are two types of schools in Azerbaijan , classified based on their ownership: public \nschools, which belong to the state and do not directly seek outside funding, and private schools , \nwhich are funded directly through education fees. \nExhibit 1: Levels of Education in Azerbaijani Schools \nLevel of Education Description2 \nPreprimary Encompasses children from birth to age 6 and is not compulsory. It is provided \nin nurseries (children under age 3), Kindergartens (children ages 3–5 or 6), and \nschools (children ages 5–6). \nPrimary Compulsory level of education that begins at age 6 and covers the first 4 years \n(Grades 1–4). \nGeneral \nSecondary \nLower Secondary Also compulsory and covers groups of students ages 10–15 (Grades 5–9). At \nthe end of Grade 9, students take final assessments to receive a document that \nis considered a basis for continuing to the next level of education. After\n\nAZERBAIJAN \nPIRLS 2021 ENCYCLOPEDIA 2 \nThere are two types of schools in Azerbaijan , classified based on their ownership: public \nschools, which belong to the state and do not directly seek outside funding, and private schools , \nwhich are funded directly through education fees. \nExhibit 1: Levels of Education in Azerbaijani Schools \nLevel of Education Description2 \nPreprimary Encompasses children from birth to age 6 and is not compulsory. It is provided \nin nurseries (children under age 3), Kindergartens (children ages 3–5 or 6), and \nschools (children ages 5–6). \nPrimary Compulsory level of education that begins at age 6 and covers the first 4 years \n(Grades 1–4). \nGeneral \nSecondary \nLower Secondary Also compulsory and covers groups of students ages 10–15 (Grades 5–9). At \nthe end of Grade 9, students take final assessments to receive a document that \nis considered a basis for continuing to the next level of education. After\n\nAZERBAIJAN \nPIRLS 2021 ENCYCLOPEDIA 2 \nThere are two types of schools in Azerbaijan , classified based on their ownership: public \nschools, which belong to the state and do not directly seek outside funding, and private schools , \nwhich are funded directly through education fees. \nExhibit 1: Levels of Education in Azerbaijani Schools \nLevel of Education Description2 \nPreprimary Encompasses children from birth to age 6 and is not compulsory. It is provided \nin nurseries (children under age 3), Kindergartens (children ages 3–5 or 6), and \nschools (children ages 5–6). \nPrimary Compulsory level of education that begins at age 6 and covers the first 4 years \n(Grades 1–4). \nGeneral \nSecondary \nLower Secondary Also compulsory and covers groups of students ages 10–15 (Grades 5–9). At \nthe end of Grade 9, students take final assessments to receive a document that \nis considered a basis for continuing to the next level of education. After'] | Q5: 1 | R5: The score is 1.00 because the first node contains the relevant information: "The context states that 'Primary Compulsory level of education that begins at age 6' and that 'Lower Secondary Also compulsory and covers groups of students ages 10–15 (Grades 5–9).' These statements provide the age at which compulsory primary education begins (age 6) and the total compulsory period (4 years of primary + 5 years of lower secondary = 9 years)." There are no irrelevant nodes to rank lower. | S5: 1 | T5: The score is 1.00 because sentence 1 is fully supported by node 1 in the retrieval context, which states that compulsory primary education starts at age 6, and by node 2, which confirms that lower secondary education is also compulsory, together accounting for the nine‑year total. | U5: 1 | V5: The score is 1.00 because the actual output perfectly aligns with the retrieval context—no contradictions were found, indicating complete faithfulness! | W5: 0 | X5: The response states that compulsory primary education lasts four years, directly contradicting the expected nine-year period and omits the total compulsory education duration. This violates both factual accuracy and completeness requirements. | Y5: 1 | Z5: The score is 1.00 because the single node ranked first contains the exact information needed: it states that "Primary Compulsory level of education that begins at age 6" and that the compulsory period lasts nine years. Since there are no irrelevant nodes ranked above it, the contextual precision reaches its maximum. | AA5: 1 | AB5: The score is 1.00 because sentence 1 of the expected output is fully supported by node 1 in the retrieval context, which explicitly states that compulsory primary education starts at age 6 and continues through the first four years, matching the description of the nine-year compulsory period. | AC5: 1 | AD5: The score is 1.00 because there are no contradictions, indicating the actual output perfectly aligns with the retrieval context! | AE5: 0.2 | AF5: The response states that compulsory primary education lasts four years, which contradicts the expected nine‑year total period, and it omits the key point about the overall duration. This mismatch and omission lower the alignment score. | AG5: 1 | AH5: The score is 1.00 because the first node contains the relevant information: "The context states that 'Primary Compulsory level of education that begins at age 6' and that 'Lower Secondary Also compulsory and covers groups of students ages 10–15 (Grades 5–9).' These statements provide the age at which compulsory primary education begins (age 6) and the total compulsory period (4 years of primary + 5 years of lower secondary = 9 years)." There are no irrelevant nodes to rank lower. | AI5: 1 | AJ5: The score is 1.00 because sentence 1 is fully supported by node 1 in the retrieval context, which states that compulsory primary education starts at age 6, and by node 2, which confirms that lower secondary education is also compulsory, together accounting for the nine‑year total. | AK5: 1 | AL5: The score is 1.00 because the actual output perfectly aligns with the retrieval context—no contradictions were found, indicating complete faithfulness! | AM5: 0 | AN5: The actual output states that compulsory primary education lasts 4 years, whereas the expected output specifies a total compulsory period of 9 years, creating a factual contradiction. Additionally, the key point about the nine‑year total duration is omitted. This mismatch leads to a low alignment score. | AO5: 1 | AP5: The score is 1.00 because the node ranked first contains the statement 'The context states that primary compulsory education begins at age 6 and covers the first 4 years, and lower secondary covers ages 10–15 (Grades 5–9), totaling nine years of compulsory education.' and there are no irrelevant nodes to rank lower. | AQ5: 1 | AR5: The score is 1.00 because sentence 1 is fully supported by node 1 in the retrieval context for the age 6 start of compulsory primary education, and by node 2 for the nine‑year total compulsory period. | AS5: 0.33333333 | AT5: The score is 0.33 because the actual output incorrectly states that compulsory primary education extends through lower secondary until age 15, whereas the context clearly limits primary education to Grades 1–4 (ages 6–10) and treats lower secondary as a separate compulsory stage. Additionally, the output claims a nine‑year primary period from age 6 to 15, which misrepresents the four‑year duration specified in the context. | AU5: 1 | AV5: The actual output correctly states that compulsory primary education starts at age 6 and lasts nine years, matching the key facts in the expected output. It adds additional context (lower secondary grades and age 15) without contradicting the expected claims, and all essential points are present. Therefore the response aligns fully with the evaluation criteria. | AW5: 1 | AX5: The score is 1.00 because the only node in the retrieval contexts (node rank 1) is relevant and is ranked first, ensuring all relevant nodes are above any irrelevant ones. The node states that "Primary Compulsory level of education that begins at age 6 and covers the first 4 years (Grades 1–4)." and that "Lower Secondary Also compulsory and covers groups of students ages 10–15 (Grades 5–9)." These details match the expected answer, so no higher score is possible. | AY5: 1 | AZ5: The score is 1.00 because sentence 1 directly matches the information in node 1 of the retrieval context, confirming that compulsory primary education starts at age 6 and lasts nine years. | BA5: 0.75 | BB5: The score is 0.75 because the actual output incorrectly states that primary education lasts ten years, which contradicts the context that primary education covers only four years (Grades 1–4) from age 6 to 10. | BC5: 0 | BD5: The actual output contradicts the expected output by stating the compulsory period lasts ten years instead of nine, and it omits the expected key point that the total period is nine years. This mismatch violates the factual comparison and key point inclusion criteria, resulting in a low score. | BE5: 1 | BF5: The score is 1.00 because the only node in the retrieval contexts (node rank 1) is relevant and is ranked first, ensuring all relevant nodes are above any irrelevant ones. The node states that "Primary Compulsory level of education that begins at age 6 and covers the first 4 years (Grades 1–4)." and that "Lower Secondary Also compulsory and covers groups of students ages 10–15 (Grades 5–9)." These details match the expected answer, so no higher score is possible. | BG5: 1 | BH5: The score is 1.00 because sentence 1 directly matches the information in node 1 of the retrieval context, confirming that compulsory primary education starts at age 6 and lasts nine years. | BI5: 1 | BJ5: The score is 1.00 because there are no contradictions, indicating the actual output perfectly aligns with the retrieval context! | BK5: 1 | BL5: The actual output correctly states that compulsory primary education starts at age 6 and that the total compulsory period is nine years, matching the key facts in the expected output. It also adds additional detail about the structure of the nine years, which does not contradict or omit any expected information. Therefore all evaluation steps are satisfied, warranting a perfect score. | BM5: synthetic
